{
  "city_id": "asheville",
  "city_name": "Asheville",
  "country": "United States",
  "scraped_at": "2026-04-30T03:32:35.396Z",
  "source": "the-infatuation",
  "places": [
    {
      "name": "Sand Hill Kitchen",
      "description": "Review for Sand Hill Kitchen",
      "category": "food-drink",
      "neighborhood": "",
      "url": "https://www.theinfatuation.com/asheville/reviews/sand-hill-kitchen"
    },
    {
      "name": "Cúrate Bar de Tapas",
      "description": "Review for Cúrate Bar de Tapas",
      "category": "food-drink",
      "neighborhood": "",
      "url": "https://www.theinfatuation.com/asheville/reviews/curate-bar-de-tapas"
    },
    {
      "name": "Neng Jr.’s",
      "description": "Review for Neng Jr.’s",
      "category": "food-drink",
      "neighborhood": "",
      "url": "https://www.theinfatuation.com/asheville/reviews/neng-jr-s"
    },
    {
      "name": "The Admiral",
      "description": "Review for The Admiral",
      "category": "food-drink",
      "neighborhood": "",
      "url": "https://www.theinfatuation.com/asheville/reviews/the-admiral"
    },
    {
      "name": "Leo's House of Thirst",
      "description": "Review for Leo's House of Thirst",
      "category": "food-drink",
      "neighborhood": "",
      "url": "https://www.theinfatuation.com/asheville/reviews/leos-house-of-thirst"
    },
    {
      "name": "Biscuit Head",
      "description": "Review for Biscuit Head",
      "category": "food-drink",
      "neighborhood": "",
      "url": "https://www.theinfatuation.com/asheville/reviews/biscuit-head"
    },
    {
      "name": "Chai Pani",
      "description": "Review for Chai Pani",
      "category": "food-drink",
      "neighborhood": "",
      "url": "https://www.theinfatuation.com/asheville/reviews/chai-pani-asheville"
    },
    {
      "name": "Sunny Point Cafe",
      "description": "Review for Sunny Point Cafe",
      "category": "food-drink",
      "neighborhood": "",
      "url": "https://www.theinfatuation.com/asheville/reviews/sunny-point-cafe"
    },
    {
      "name": "Baby Bull",
      "description": "Review for Baby Bull",
      "category": "food-drink",
      "neighborhood": "",
      "url": "https://www.theinfatuation.com/asheville/reviews/baby-bull"
    },
    {
      "name": "All Souls Pizza",
      "description": "Review for All Souls Pizza",
      "category": "food-drink",
      "neighborhood": "",
      "url": "https://www.theinfatuation.com/asheville/reviews/all-souls-pizza"
    },
    {
      "name": "12 Bones Smokehouse",
      "description": "Review for 12 Bones Smokehouse",
      "category": "food-drink",
      "neighborhood": "",
      "url": "https://www.theinfatuation.com/asheville/reviews/12-bones-smokehouse"
    },
    {
      "name": "Rosetta's Kitchen",
      "description": "Review for Rosetta's Kitchen",
      "category": "food-drink",
      "neighborhood": "",
      "url": "https://www.theinfatuation.com/asheville/reviews/rosettas-kitchen"
    },
    {
      "name": "Taco Billy",
      "description": "Review for Taco Billy",
      "category": "food-drink",
      "neighborhood": "",
      "url": "https://www.theinfatuation.com/asheville/reviews/taco-billy"
    }
  ]
}