{
  "city_id": "cleveland",
  "city_name": "Cleveland",
  "country": "United States",
  "scraped_at": "2026-04-08T11:32:51.857Z",
  "source": "the-infatuation",
  "places": [
    {
      "name": "Cordelia",
      "description": "Review for Cordelia",
      "category": "food-drink",
      "neighborhood": "",
      "url": "https://www.theinfatuation.com/cleveland/reviews/cordelia"
    },
    {
      "name": "Great Lakes Brewing Company",
      "description": "Review for Great Lakes Brewing Company",
      "category": "food-drink",
      "neighborhood": "",
      "url": "https://www.theinfatuation.com/cleveland/reviews/great-lakes-brewing-company"
    },
    {
      "name": "Fahrenheit",
      "description": "Review for Fahrenheit",
      "category": "food-drink",
      "neighborhood": "",
      "url": "https://www.theinfatuation.com/cleveland/reviews/fahrenheit"
    },
    {
      "name": "Mabel's BBQ",
      "description": "Review for Mabel's BBQ",
      "category": "food-drink",
      "neighborhood": "",
      "url": "https://www.theinfatuation.com/cleveland/reviews/mabels-bbq-cleveland"
    },
    {
      "name": "Larder Delicatessen and Bakery",
      "description": "Review for Larder Delicatessen and Bakery",
      "category": "food-drink",
      "neighborhood": "",
      "url": "https://www.theinfatuation.com/cleveland/reviews/larder-delicatessen"
    },
    {
      "name": "Vero Pizza Napoletana",
      "description": "Review for Vero Pizza Napoletana",
      "category": "food-drink",
      "neighborhood": "",
      "url": "https://www.theinfatuation.com/cleveland/reviews/vero-pizza-napoletana"
    },
    {
      "name": "Abundance Culinary",
      "description": "Review for Abundance Culinary",
      "category": "food-drink",
      "neighborhood": "",
      "url": "https://www.theinfatuation.com/cleveland/reviews/abundance-culinary"
    },
    {
      "name": "Marble Room",
      "description": "Review for Marble Room",
      "category": "food-drink",
      "neighborhood": "",
      "url": "https://www.theinfatuation.com/cleveland/reviews/marble-room"
    },
    {
      "name": "Poppy",
      "description": "Review for Poppy",
      "category": "food-drink",
      "neighborhood": "",
      "url": "https://www.theinfatuation.com/cleveland/reviews/poppy-cleveland"
    },
    {
      "name": "El Arepazo Y Pupuseria",
      "description": "Review for El Arepazo Y Pupuseria",
      "category": "food-drink",
      "neighborhood": "",
      "url": "https://www.theinfatuation.com/cleveland/reviews/el-arepazo-y-pupuseria"
    },
    {
      "name": "Amba",
      "description": "Review for Amba",
      "category": "food-drink",
      "neighborhood": "",
      "url": "https://www.theinfatuation.com/cleveland/reviews/amba-cleveland"
    },
    {
      "name": "Herb'n Twine",
      "description": "Review for Herb'n Twine",
      "category": "food-drink",
      "neighborhood": "",
      "url": "https://www.theinfatuation.com/cleveland/reviews/herbn-twine"
    },
    {
      "name": "Batuqui",
      "description": "Review for Batuqui",
      "category": "food-drink",
      "neighborhood": "",
      "url": "https://www.theinfatuation.com/cleveland/reviews/batuqui"
    },
    {
      "name": "Thai Thai",
      "description": "Review for Thai Thai",
      "category": "food-drink",
      "neighborhood": "",
      "url": "https://www.theinfatuation.com/cleveland/reviews/thai-thai"
    },
    {
      "name": "Ginko",
      "description": "Review for Ginko",
      "category": "food-drink",
      "neighborhood": "",
      "url": "https://www.theinfatuation.com/cleveland/reviews/ginko"
    },
    {
      "name": "Birdietown",
      "description": "Review for Birdietown",
      "category": "food-drink",
      "neighborhood": "",
      "url": "https://www.theinfatuation.com/cleveland/reviews/birdietown"
    },
    {
      "name": "Patron Saint",
      "description": "Review for Patron Saint",
      "category": "food-drink",
      "neighborhood": "",
      "url": "https://www.theinfatuation.com/cleveland/reviews/patron-saint"
    },
    {
      "name": "Zoma Ethiopian Restaurant",
      "description": "Review for Zoma Ethiopian Restaurant",
      "category": "food-drink",
      "neighborhood": "",
      "url": "https://www.theinfatuation.com/cleveland/reviews/zoma-ethiopian-restaurant"
    },
    {
      "name": "The Rowley Inn",
      "description": "Review for The Rowley Inn",
      "category": "food-drink",
      "neighborhood": "",
      "url": "https://www.theinfatuation.com/cleveland/reviews/rowley-inn"
    },
    {
      "name": "Superior Pho",
      "description": "Review for Superior Pho",
      "category": "food-drink",
      "neighborhood": "",
      "url": "https://www.theinfatuation.com/cleveland/reviews/superior-pho"
    },
    {
      "name": "Porco Lounge & Tiki Room",
      "description": "Review for Porco Lounge & Tiki Room",
      "category": "food-drink",
      "neighborhood": "",
      "url": "https://www.theinfatuation.com/cleveland/reviews/porco-lounge-and-tiki-room"
    },
    {
      "name": "Cloak & Dagger",
      "description": "Review for Cloak & Dagger",
      "category": "food-drink",
      "neighborhood": "",
      "url": "https://www.theinfatuation.com/cleveland/reviews/cloak-and-dagger"
    },
    {
      "name": "Prosperity Social Club",
      "description": "Review for Prosperity Social Club",
      "category": "food-drink",
      "neighborhood": "",
      "url": "https://www.theinfatuation.com/cleveland/reviews/prosperity-social-club"
    },
    {
      "name": "Good Night John Boy",
      "description": "Review for Good Night John Boy",
      "category": "food-drink",
      "neighborhood": "",
      "url": "https://www.theinfatuation.com/cleveland/reviews/good-night-john-boy-cleveland"
    }
  ]
}