{
  "city_id": "zurich",
  "city_name": "Zurich",
  "country": "Switzerland",
  "scraped_at": "2026-03-29T01:04:20.447Z",
  "source": "atlas-obscura",
  "places": [
    {
      "name": "Cabaret Voltaire: the Dada House",
      "description": "One hundred years ago this small house in downtown Z\u00fcrich became the birthplace of the Dada movement.",
      "location": "ZURICH, SWITZERLAND",
      "tags": [],
      "url": ""
    },
    {
      "name": "Oepfelchammer",
      "description": "A 200-year-old tavern challenges guests to finish a glass of wine while hanging from a ceiling beam.",
      "location": "ZURICH, SWITZERLAND",
      "tags": [],
      "url": ""
    },
    {
      "name": "MFO Park",
      "description": "Vines grow up the metal bars in this public park created from an old machine factory.",
      "location": "ZURICH, SWITZERLAND",
      "tags": [],
      "url": ""
    },
    {
      "name": "Moulagenmuseum",
      "description": "Museum dedicated to wax representations of disfiguring diseases.",
      "location": "ZURICH, SWITZERLAND",
      "tags": [],
      "url": ""
    },
    {
      "name": "Sukkulenten-Sammlung Z\u00fcrich",
      "description": "See the rare bloom of the \"Queen of the Night\" cactus at one of the world's largest succulent collections.",
      "location": "ZURICH, SWITZERLAND",
      "tags": [],
      "url": ""
    },
    {
      "name": "Haus Hiltl",
      "description": "Featuring a meatless buffet fit for kings, this family-owned Zurich eatery is considered the oldest vegetarian restaurant in the West.",
      "location": "ZURICH, SWITZERLAND",
      "tags": [],
      "url": ""
    },
    {
      "name": "Schr\u00f6dinger's Cat",
      "description": "Hidden in the garden of physicist Erwin Schr\u00f6dinger's house is a life-size figure of a cat from his famous thought experiment.",
      "location": "ZURICH, SWITZERLAND",
      "tags": [],
      "url": ""
    },
    {
      "name": "M\u00fchlerama Museum",
      "description": "Grind your own flour to bake your own bread at a 100-year-old mill.",
      "location": "ZURICH, SWITZERLAND",
      "tags": [],
      "url": ""
    }
  ]
}