{
  "neighborhoods": [
    {
      "id": "nob-hill",
      "city_id": "albuquerque",
      "name": {
        "en": "Nob Hill"
      },
      "summary": {
        "en": "Historic Route 66 neon-and-chrome nostalgia collides with a modern, sophisticated energy. This highly walkable district is buzzing with university students, young professionals, and a thriving independent dining scene."
      },
      "lat": 35.0841,
      "lng": -106.6204,
      "trending_score": 95
    },
    {
      "id": "downtown-west-downtown",
      "city_id": "albuquerque",
      "name": {
        "en": "Downtown & West Downtown"
      },
      "summary": {
        "en": "A neighborhood of contrasts, where historic theaters and gritty alleyways meet sleek new bars and corporate high-rises. By day it's the city's business core; by night it reveals its hidden gems."
      },
      "lat": 35.0865,
      "lng": -106.652,
      "trending_score": 88
    },
    {
      "id": "university-area",
      "city_id": "albuquerque",
      "name": {
        "en": "University Area"
      },
      "summary": {
        "en": "Unpretentious, energetic, and defined by the rhythms of the University of New Mexico. This area is home to timeless Albuquerque institutions, cheap eats, and the beautiful, historic campus."
      },
      "lat": 35.0844,
      "lng": -106.6247,
      "trending_score": 85
    },
    {
      "id": "barelas",
      "city_id": "albuquerque",
      "name": {
        "en": "Barelas"
      },
      "summary": {
        "en": "Deeply historic and culturally rich, Barelas is one of Albuquerque's oldest Hispanic neighborhoods. The air here feels thick with history, from the old railroad tracks to the generations-old adobes."
      },
      "lat": 35.075,
      "lng": -106.655,
      "trending_score": 78
    },
    {
      "id": "international-district",
      "city_id": "albuquerque",
      "name": {
        "en": "International District"
      },
      "summary": {
        "en": "A sprawling, diverse, and unpretentious neighborhood that is Albuquerque's true culinary melting pot. The magic here is in unassuming strip malls where you'll find the city's most authentic global cuisine."
      },
      "lat": 35.078,
      "lng": -106.585,
      "trending_score": 82
    },
    {
      "id": "old-town-sawmill",
      "city_id": "albuquerque",
      "name": {
        "en": "Old Town & Sawmill Market Area"
      },
      "summary": {
        "en": "Experience Albuquerque's historic heart by exploring its quieter backstreets, hidden courtyards, and the revitalized industrial-chic Sawmill district just to the north."
      },
      "lat": 35.099,
      "lng": -106.668,
      "trending_score": 92
    }
  ],
  "waypoints": [
    {
      "id": "nob-hill-ihatov-bread-and-coffee",
      "city_id": "albuquerque",
      "neighborhood_id": "nob-hill",
      "name": {
        "en": "Ihatov Bread And Coffee"
      },
      "description": {
        "en": "A serene and minimalist Japanese- and French-style bakery, perfect for a meticulously crafted espresso drink and an exquisite pastry."
      },
      "type": "drink",
      "lat": 35.0842,
      "lng": -106.613,
      "trending_score": 90
    },
    {
      "id": "nob-hill-mesa-provisions",
      "city_id": "albuquerque",
      "neighborhood_id": "nob-hill",
      "name": {
        "en": "Mesa Provisions"
      },
      "description": {
        "en": "An upscale but comfortable American restaurant focusing on seasonal ingredients and thoughtfully composed dishes that elevate local flavors."
      },
      "type": "food",
      "lat": 35.084,
      "lng": -106.621,
      "trending_score": 88
    },
    {
      "id": "nob-hill-frenchish",
      "city_id": "albuquerque",
      "neighborhood_id": "nob-hill",
      "name": {
        "en": "Frenchish"
      },
      "description": {
        "en": "A lively neighborhood bistro that playfully deconstructs French cuisine with a fun, accessible menu that doesn't take itself too seriously."
      },
      "type": "food",
      "lat": 35.0841,
      "lng": -106.623,
      "trending_score": 85
    },
    {
      "id": "nob-hill-manana-taco",
      "city_id": "albuquerque",
      "neighborhood_id": "nob-hill",
      "name": {
        "en": "Mañana Taco"
      },
      "description": {
        "en": "An essential food truck serving Austin-style breakfast tacos. It’s a local morning ritual and the perfect fuel for a day of walking."
      },
      "type": "food",
      "lat": 35.0843,
      "lng": -106.618,
      "trending_score": 92
    },
    {
      "id": "nob-hill-route-66-neon-signs",
      "city_id": "albuquerque",
      "neighborhood_id": "nob-hill",
      "name": {
        "en": "Route 66 Neon Signs"
      },
      "description": {
        "en": "Walk Central Avenue at dusk to hunt for beautifully restored and retro-style neon signs that hark back to the Mother Road's heyday."
      },
      "type": "landmark",
      "lat": 35.0841,
      "lng": -106.6204,
      "trending_score": 94
    },
    {
      "id": "nob-hill-pueblo-deco-architecture",
      "city_id": "albuquerque",
      "neighborhood_id": "nob-hill",
      "name": {
        "en": "Pueblo Deco Architecture"
      },
      "description": {
        "en": "Look beyond the storefronts to spot a unique blend of Art Deco geometry and Southwestern motifs, like geometric patterns and rounded corners."
      },
      "type": "culture",
      "lat": 35.084,
      "lng": -106.622,
      "trending_score": 80
    },
    {
      "id": "nob-hill-alleyway-art",
      "city_id": "albuquerque",
      "neighborhood_id": "nob-hill",
      "name": {
        "en": "Alleyway Art"
      },
      "description": {
        "en": "Duck into the alleys just off Central Avenue to find small, unexpected murals and street art hidden from the main-street bustle."
      },
      "type": "hidden_gem",
      "lat": 35.0838,
      "lng": -106.619,
      "trending_score": 82
    },
    {
      "id": "downtown-west-downtown-dwtnr",
      "city_id": "albuquerque",
      "neighborhood_id": "downtown-west-downtown",
      "name": {
        "en": "DWTNR"
      },
      "description": {
        "en": "A chic, retro-inspired bar located inside the Arrive hotel, it’s a stylish spot to grab a well-crafted cocktail."
      },
      "type": "nightlife",
      "lat": 35.087,
      "lng": -106.65,
      "trending_score": 85
    },
    {
      "id": "downtown-west-downtown-farina-pizzeria",
      "city_id": "albuquerque",
      "neighborhood_id": "downtown-west-downtown",
      "name": {
        "en": "Farina Pizzeria & Wine Bar"
      },
      "description": {
        "en": "A bustling, modern pizzeria that's a local favorite for its fantastic thin-crust pizzas and excellent wine selection."
      },
      "type": "food",
      "lat": 35.0875,
      "lng": -106.645,
      "trending_score": 90
    },
    {
      "id": "downtown-west-downtown-duran-central-pharmacy",
      "city_id": "albuquerque",
      "neighborhood_id": "downtown-west-downtown",
      "name": {
        "en": "Duran Central Pharmacy"
      },
      "description": {
        "en": "A working pharmacy with a beloved New Mexican diner hidden in the back, serving some of the city's best red chile to loyal locals."
      },
      "type": "hidden_gem",
      "lat": 35.092,
      "lng": -106.662,
      "trending_score": 98
    },
    {
      "id": "downtown-west-downtown-the-mouse-hole",
      "city_id": "albuquerque",
      "neighborhood_id": "downtown-west-downtown",
      "name": {
        "en": "The Mouse Hole"
      },
      "description": {
        "en": "Albuquerque's 'teeny tiny fromagerie,' this closet-sized cheese shop is a true hidden gem offering an expertly curated selection."
      },
      "type": "shopping",
      "lat": 35.0925,
      "lng": -106.661,
      "trending_score": 88
    },
    {
      "id": "downtown-west-downtown-kimo-theatre",
      "city_id": "albuquerque",
      "neighborhood_id": "downtown-west-downtown",
      "name": {
        "en": "KiMo Theatre Façade"
      },
      "description": {
        "en": "A spectacular example of Pueblo Deco architecture covered in symbolic ornamentation, from stylized birds to Native American motifs."
      },
      "type": "landmark",
      "lat": 35.086,
      "lng": -106.649,
      "trending_score": 93
    },
    {
      "id": "university-area-frontier-restaurant",
      "city_id": "albuquerque",
      "neighborhood_id": "university-area",
      "name": {
        "en": "Frontier Restaurant"
      },
      "description": {
        "en": "An Albuquerque icon since 1971, this counter-service spot is famous for its green chile stew, breakfast burritos, and sweet rolls."
      },
      "type": "food",
      "lat": 35.0845,
      "lng": -106.626,
      "trending_score": 100
    },
    {
      "id": "university-area-el-patio",
      "city_id": "albuquerque",
      "neighborhood_id": "university-area",
      "name": {
        "en": "El Patio"
      },
      "description": {
        "en": "A beloved institution since the 1970s where locals flock for what many consider the best sopaipillas in New Mexico."
      },
      "type": "food",
      "lat": 35.082,
      "lng": -106.627,
      "trending_score": 89
    },
    {
      "id": "university-area-art-of-frontier",
      "city_id": "albuquerque",
      "neighborhood_id": "university-area",
      "name": {
        "en": "The Art of Frontier"
      },
      "description": {
        "en": "The famous restaurant doubles as an informal art gallery; wander its rooms to see a vast collection of local art and John Wayne portraits."
      },
      "type": "culture",
      "lat": 35.0846,
      "lng": -106.626,
      "trending_score": 85
    },
    {
      "id": "university-area-unm-campus",
      "city_id": "albuquerque",
      "neighborhood_id": "university-area",
      "name": {
        "en": "UNM's Pueblo Revival Campus"
      },
      "description": {
        "en": "The main UNM campus is an architectural museum of unique Pueblo Revival style, characterized by adobe-like stucco, flat roofs, and heavy timbers."
      },
      "type": "landmark",
      "lat": 35.083,
      "lng": -106.62,
      "trending_score": 88
    },
    {
      "id": "university-area-the-duck-pond",
      "city_id": "albuquerque",
      "neighborhood_id": "university-area",
      "name": {
        "en": "The Duck Pond"
      },
      "description": {
        "en": "A serene oasis in the heart of the bustling UNM campus, perfect for taking a break under a cottonwood tree."
      },
      "type": "nature",
      "lat": 35.085,
      "lng": -106.621,
      "trending_score": 75
    },
    {
      "id": "barelas-el-modelo",
      "city_id": "albuquerque",
      "neighborhood_id": "barelas",
      "name": {
        "en": "El Modelo Mexican Foods"
      },
      "description": {
        "en": "A legendary take-out institution since 1929 with a near-permanent line of locals waiting for massive, perfectly seasoned tamales."
      },
      "type": "food",
      "lat": 35.078,
      "lng": -106.655,
      "trending_score": 96
    },
    {
      "id": "barelas-hispanic-cultural-center",
      "city_id": "albuquerque",
      "neighborhood_id": "barelas",
      "name": {
        "en": "National Hispanic Cultural Center"
      },
      "description": {
        "en": "The cultural heart of the neighborhood, featuring a tower with a breathtaking fresco depicting the visual history of the Hispanic world."
      },
      "type": "culture",
      "lat": 35.073,
      "lng": -106.658,
      "trending_score": 90
    },
    {
      "id": "barelas-rail-yards",
      "city_id": "albuquerque",
      "neighborhood_id": "barelas",
      "name": {
        "en": "The Albuquerque Rail Yards"
      },
      "description": {
        "en": "A massive, ghostly complex where the city's story as a railroad town began. Walking the perimeter is an atmospheric experience."
      },
      "type": "landmark",
      "lat": 35.071,
      "lng": -106.652,
      "trending_score": 87
    },
    {
      "id": "barelas-south-fourth-street",
      "city_id": "albuquerque",
      "neighborhood_id": "barelas",
      "name": {
        "en": "Barelas-South Fourth Street"
      },
      "description": {
        "en": "Walk the main commercial street to see historic buildings that once served the bustling railroad community a century ago."
      },
      "type": "landmark",
      "lat": 35.076,
      "lng": -106.655,
      "trending_score": 70
    },
    {
      "id": "international-district-coda-bakery",
      "city_id": "albuquerque",
      "neighborhood_id": "international-district",
      "name": {
        "en": "Coda Bakery"
      },
      "description": {
        "en": "A top-tier Vietnamese bakery serving potent iced coffee and what many locals declare is the best báhn mì in Albuquerque."
      },
      "type": "food",
      "lat": 35.081,
      "lng": -106.589,
      "trending_score": 91
    },
    {
      "id": "international-district-red-rock-deli",
      "city_id": "albuquerque",
      "neighborhood_id": "international-district",
      "name": {
        "en": "Red Rock Deli"
      },
      "description": {
        "en": "A rare find in the Southwest, this Eastern European market and cafe serves incredible homemade pierogi, borscht, and stuffed cabbage."
      },
      "type": "food",
      "lat": 35.072,
      "lng": -106.587,
      "trending_score": 89
    },
    {
      "id": "international-district-market-hop",
      "city_id": "albuquerque",
      "neighborhood_id": "international-district",
      "name": {
        "en": "International Market Hop"
      },
      "description": {
        "en": "The real discovery is to step inside the neighborhood's many grocery stores to browse spices, snacks, and ingredients from around the world."
      },
      "type": "shopping",
      "lat": 35.079,
      "lng": -106.586,
      "trending_score": 80
    },
    {
      "id": "international-district-central-ave-murals",
      "city_id": "albuquerque",
      "neighborhood_id": "international-district",
      "name": {
        "en": "The Murals of Central Avenue"
      },
      "description": {
        "en": "The walls of businesses are adorned with vibrant murals depicting the cultures and stories of the diverse communities in the district."
      },
      "type": "culture",
      "lat": 35.08,
      "lng": -106.588,
      "trending_score": 84
    },
    {
      "id": "international-district-expo-new-mexico",
      "city_id": "albuquerque",
      "neighborhood_id": "international-district",
      "name": {
        "en": "Expo New Mexico"
      },
      "description": {
        "en": "On the edge of the district, the state fairgrounds feature quirky, large-scale sculptures and unique architecture from decades of state fairs."
      },
      "type": "landmark",
      "lat": 35.082,
      "lng": -106.575,
      "trending_score": 72
    },
    {
      "id": "old-town-sawmill-tiny-grocer-abq",
      "city_id": "albuquerque",
      "neighborhood_id": "old-town-sawmill",
      "name": {
        "en": "Tiny Grocer ABQ"
      },
      "description": {
        "en": "A secret haven just off the main Old Town drag, this independent grocery and cafe is perfect for a high-quality coffee or a light lunch."
      },
      "type": "food",
      "lat": 35.098,
      "lng": -106.666,
      "trending_score": 86
    },
    {
      "id": "old-town-sawmill-indian-pueblo-kitchen",
      "city_id": "albuquerque",
      "neighborhood_id": "old-town-sawmill",
      "name": {
        "en": "Indian Pueblo Kitchen"
      },
      "description": {
        "en": "A vital culinary center offering a rare opportunity to experience modern and traditional Indigenous cuisine from New Mexico's 19 Pueblos."
      },
      "type": "culture",
      "lat": 35.106,
      "lng": -106.663,
      "trending_score": 95
    },
    {
      "id": "old-town-sawmill-hidden-courtyards",
      "city_id": "albuquerque",
      "neighborhood_id": "old-town-sawmill",
      "name": {
        "en": "Hidden Courtyards (Placitas)"
      },
      "description": {
        "en": "The magic of Old Town is found by ducking off the main plaza into smaller, sun-dappled courtyards with fountains and artisan shops."
      },
      "type": "hidden_gem",
      "lat": 35.097,
      "lng": -106.669,
      "trending_score": 90
    },
    {
      "id": "old-town-sawmill-sawmill-market",
      "city_id": "albuquerque",
      "neighborhood_id": "old-town-sawmill",
      "name": {
        "en": "Sawmill Market"
      },
      "description": {
        "en": "A stunningly restored former lumber mill, now a bustling food hall with modern, industrial energy and a hub for local food vendors."
      },
      "type": "food",
      "lat": 35.101,
      "lng": -106.665,
      "trending_score": 98
    },
    {
      "id": "old-town-sawmill-quiet-backstreets",
      "city_id": "albuquerque",
      "neighborhood_id": "old-town-sawmill",
      "name": {
        "en": "The Quiet Backstreets"
      },
      "description": {
        "en": "Wander the residential streets to find beautiful, historic adobe homes with colorful doors and strings of chile ristras."
      },
      "type": "landmark",
      "lat": 35.098,
      "lng": -106.667,
      "trending_score": 82
    }
  ],
  "tasks": [
    {
      "id": "nob-hill-task-1",
      "neighborhood_id": "nob-hill",
      "title": {
        "en": "Neon Glow"
      },
      "prompt": {
        "en": "Find a classic Route 66 neon sign and take a photo that captures its retro glow."
      },
      "points": 10,
      "duration_minutes": 5
    },
    {
      "id": "nob-hill-task-2",
      "neighborhood_id": "nob-hill",
      "title": {
        "en": "Pueblo Deco Detail"
      },
      "prompt": {
        "en": "Look up! Find an interesting architectural detail on a building that blends Art Deco and Southwestern styles and snap a picture of it."
      },
      "points": 10,
      "duration_minutes": 5
    },
    {
      "id": "nob-hill-task-3",
      "neighborhood_id": "nob-hill",
      "title": {
        "en": "Hipster Fuel"
      },
      "prompt": {
        "en": "Take a photo of your coffee or snack from an independent cafe that perfectly captures the neighborhood's trendy vibe."
      },
      "points": 10,
      "duration_minutes": 5
    },
    {
      "id": "nob-hill-task-4",
      "neighborhood_id": "nob-hill",
      "title": {
        "en": "Alleyway Explorer"
      },
      "prompt": {
        "en": "Venture into an alley off Central Avenue and find a piece of hidden street art or a cool mural. Capture it."
      },
      "points": 10,
      "duration_minutes": 5
    },
    {
      "id": "nob-hill-task-5",
      "neighborhood_id": "nob-hill",
      "title": {
        "en": "Mother Road Selfie"
      },
      "prompt": {
        "en": "Take a selfie with a Route 66 marker or sign in the background."
      },
      "points": 10,
      "duration_minutes": 5
    },
    {
      "id": "nob-hill-task-6",
      "neighborhood_id": "nob-hill",
      "title": {
        "en": "Shop Small"
      },
      "prompt": {
        "en": "Find a unique item in the window of a local, independent shop and take an artistic photo of the display."
      },
      "points": 10,
      "duration_minutes": 5
    },
    {
      "id": "nob-hill-task-7",
      "neighborhood_id": "nob-hill",
      "title": {
        "en": "Then and Now"
      },
      "prompt": {
        "en": "Capture a single photo that shows both a historic building and a modern element of Nob Hill."
      },
      "points": 10,
      "duration_minutes": 5
    },
    {
      "id": "nob-hill-task-8",
      "neighborhood_id": "nob-hill",
      "title": {
        "en": "Student Life"
      },
      "prompt": {
        "en": "Take a photo that represents the university energy of the neighborhood."
      },
      "points": 10,
      "duration_minutes": 5
    },
    {
      "id": "nob-hill-task-9",
      "neighborhood_id": "nob-hill",
      "title": {
        "en": "Reflections of Route 66"
      },
      "prompt": {
        "en": "Find a reflection of a neon sign in a puddle or a shop window and take a creative shot."
      },
      "points": 10,
      "duration_minutes": 5
    },
    {
      "id": "nob-hill-task-10",
      "neighborhood_id": "nob-hill",
      "title": {
        "en": "Quirky Character"
      },
      "prompt": {
        "en": "Photograph something you find that is uniquely quirky or eccentric, representing the neighborhood's spirit."
      },
      "points": 10,
      "duration_minutes": 5
    },
    {
      "id": "nob-hill-task-11",
      "neighborhood_id": "nob-hill",
      "title": {
        "en": "Street Style"
      },
      "prompt": {
        "en": "Capture a candid photo of the fashion or style of the people walking in Nob Hill."
      },
      "points": 10,
      "duration_minutes": 5
    },
    {
      "id": "nob-hill-task-12",
      "neighborhood_id": "nob-hill",
      "title": {
        "en": "Patio Life"
      },
      "prompt": {
        "en": "Find a bustling cafe or restaurant patio and take a picture that captures the social energy."
      },
      "points": 10,
      "duration_minutes": 5
    },
    {
      "id": "nob-hill-task-13",
      "neighborhood_id": "nob-hill",
      "title": {
        "en": "Geometric Shapes"
      },
      "prompt": {
        "en": "Focus on the Pueblo Deco style and take a photo composed entirely of geometric shapes you find on a building."
      },
      "points": 10,
      "duration_minutes": 5
    },
    {
      "id": "nob-hill-task-14",
      "neighborhood_id": "nob-hill",
      "title": {
        "en": "Food Truck Find"
      },
      "prompt": {
        "en": "Spot a food truck and take a photo that makes its food look irresistible."
      },
      "points": 10,
      "duration_minutes": 5
    },
    {
      "id": "nob-hill-task-15",
      "neighborhood_id": "nob-hill",
      "title": {
        "en": "Dusk on Central"
      },
      "prompt": {
        "en": "As the sun sets, take a photo of the streetlights and neon signs beginning to turn on along Central Ave."
      },
      "points": 10,
      "duration_minutes": 5
    },
    {
      "id": "downtown-west-downtown-task-1",
      "neighborhood_id": "downtown-west-downtown",
      "title": {
        "en": "Urban Contrast"
      },
      "prompt": {
        "en": "Take a photo that shows a sharp contrast between old and new architecture in the neighborhood."
      },
      "points": 10,
      "duration_minutes": 5
    },
    {
      "id": "downtown-west-downtown-task-2",
      "neighborhood_id": "downtown-west-downtown",
      "title": {
        "en": "Hidden Gem Selfie"
      },
      "prompt": {
        "en": "Find a place that feels like a secret (a tiny shop, a quiet alley, a hidden diner) and take a selfie there."
      },
      "points": 10,
      "duration_minutes": 5
    },
    {
      "id": "downtown-west-downtown-task-3",
      "neighborhood_id": "downtown-west-downtown",
      "title": {
        "en": "Look Up!"
      },
      "prompt": {
        "en": "Stand at the base of a tall building and take a photo looking straight up to the sky."
      },
      "points": 10,
      "duration_minutes": 5
    },
    {
      "id": "downtown-west-downtown-task-4",
      "neighborhood_id": "downtown-west-downtown",
      "title": {
        "en": "Gritty Beauty"
      },
      "prompt": {
        "en": "Find beauty in an unexpected place, like a textured brick wall, a fire escape, or a piece of street art in an alley."
      },
      "points": 10,
      "duration_minutes": 5
    },
    {
      "id": "downtown-west-downtown-task-5",
      "neighborhood_id": "downtown-west-downtown",
      "title": {
        "en": "Theater Marquee"
      },
      "prompt": {
        "en": "Photograph the marquee of a historic theater, focusing on the intricate details."
      },
      "points": 10,
      "duration_minutes": 5
    },
    {
      "id": "downtown-west-downtown-task-6",
      "neighborhood_id": "downtown-west-downtown",
      "title": {
        "en": "Business vs. Leisure"
      },
      "prompt": {
        "en": "Capture a scene that shows the mix of business (people in suits, office buildings) and leisure (a bar patio, a park) in Downtown."
      },
      "points": 10,
      "duration_minutes": 5
    },
    {
      "id": "downtown-west-downtown-task-7",
      "neighborhood_id": "downtown-west-downtown",
      "title": {
        "en": "Cocktail Hour"
      },
      "prompt": {
        "en": "Take a stylish photo of a drink at a chic downtown bar."
      },
      "points": 10,
      "duration_minutes": 5
    },
    {
      "id": "downtown-west-downtown-task-8",
      "neighborhood_id": "downtown-west-downtown",
      "title": {
        "en": "Urban Reflection"
      },
      "prompt": {
        "en": "Find a glass building and capture the reflection of the surrounding cityscape in it."
      },
      "points": 10,
      "duration_minutes": 5
    },
    {
      "id": "downtown-west-downtown-task-9",
      "neighborhood_id": "downtown-west-downtown",
      "title": {
        "en": "Secret Entrance"
      },
      "prompt": {
        "en": "Find a doorway or entrance that looks mysterious or unassuming and take a photo of it."
      },
      "points": 10,
      "duration_minutes": 5
    },
    {
      "id": "downtown-west-downtown-task-10",
      "neighborhood_id": "downtown-west-downtown",
      "title": {
        "en": "Streetlight Shadows"
      },
      "prompt": {
        "en": "As evening approaches, play with light and shadow. Take a photo of the long shadows cast by streetlights or buildings."
      },
      "points": 10,
      "duration_minutes": 5
    },
    {
      "id": "downtown-west-downtown-task-11",
      "neighborhood_id": "downtown-west-downtown",
      "title": {
        "en": "City Life"
      },
      "prompt": {
        "en": "Take a photo that captures the motion and energy of a busy downtown street corner."
      },
      "points": 10,
      "duration_minutes": 5
    },
    {
      "id": "downtown-west-downtown-task-12",
      "neighborhood_id": "downtown-west-downtown",
      "title": {
        "en": "Architectural Icon"
      },
      "prompt": {
        "en": "Find the most interesting building in the neighborhood and take a photo of it from a unique angle."
      },
      "points": 10,
      "duration_minutes": 5
    },
    {
      "id": "downtown-west-downtown-task-13",
      "neighborhood_id": "downtown-west-downtown",
      "title": {
        "en": "Urban Foodie"
      },
      "prompt": {
        "en": "Capture a delicious-looking meal from a downtown eatery, with the urban environment visible in the background."
      },
      "points": 10,
      "duration_minutes": 5
    },
    {
      "id": "downtown-west-downtown-task-14",
      "neighborhood_id": "downtown-west-downtown",
      "title": {
        "en": "Signs of the City"
      },
      "prompt": {
        "en": "Create a photo collage of three different interesting signs you find (street signs, shop signs, neon signs)."
      },
      "points": 10,
      "duration_minutes": 5
    },
    {
      "id": "downtown-west-downtown-task-15",
      "neighborhood_id": "downtown-west-downtown",
      "title": {
        "en": "Night Owl"
      },
      "prompt": {
        "en": "After dark, take a photo that captures the nightlife vibe of the neighborhood."
      },
      "points": 10,
      "duration_minutes": 5
    },
    {
      "id": "university-area-task-1",
      "neighborhood_id": "university-area",
      "title": {
        "en": "Campus Landmark"
      },
      "prompt": {
        "en": "Find a building on the UNM campus that exemplifies the Pueblo Revival style and take a photo."
      },
      "points": 10,
      "duration_minutes": 5
    },
    {
      "id": "university-area-task-2",
      "neighborhood_id": "university-area",
      "title": {
        "en": "Student Hangout"
      },
      "prompt": {
        "en": "Capture the atmosphere of a place buzzing with student energy, like a busy cafe or a spot on campus."
      },
      "points": 10,
      "duration_minutes": 5
    },
    {
      "id": "university-area-task-3",
      "neighborhood_id": "university-area",
      "title": {
        "en": "Iconic Bite"
      },
      "prompt": {
        "en": "Take a mouth-watering photo of a classic neighborhood food item, like a breakfast burrito or a sweet roll."
      },
      "points": 10,
      "duration_minutes": 5
    },
    {
      "id": "university-area-task-4",
      "neighborhood_id": "university-area",
      "title": {
        "en": "Study Break"
      },
      "prompt": {
        "en": "Find a peaceful spot on campus, like near the Duck Pond, and take a photo that feels calm and serene."
      },
      "points": 10,
      "duration_minutes": 5
    },
    {
      "id": "university-area-task-5",
      "neighborhood_id": "university-area",
      "title": {
        "en": "Lobo Pride"
      },
      "prompt": {
        "en": "Find and photograph the UNM logo or a cherry-and-silver Lobo mascot somewhere in the neighborhood."
      },
      "points": 10,
      "duration_minutes": 5
    },
    {
      "id": "university-area-task-6",
      "neighborhood_id": "university-area",
      "title": {
        "en": "Art Walk"
      },
      "prompt": {
        "en": "Discover a piece of public art or a quirky painting inside a local restaurant and snap a picture."
      },
      "points": 10,
      "duration_minutes": 5
    },
    {
      "id": "university-area-task-7",
      "neighborhood_id": "university-area",
      "title": {
        "en": "Architectural Details"
      },
      "prompt": {
        "en": "Get a close-up shot of the unique architectural elements of a campus building, like heavy timbers (vigas) or adobe-like stucco."
      },
      "points": 10,
      "duration_minutes": 5
    },
    {
      "id": "university-area-task-8",
      "neighborhood_id": "university-area",
      "title": {
        "en": "Neighborhood Living Room"
      },
      "prompt": {
        "en": "Take a photo inside a local institution that captures its role as a community gathering place."
      },
      "points": 10,
      "duration_minutes": 5
    },
    {
      "id": "university-area-task-9",
      "neighborhood_id": "university-area",
      "title": {
        "en": "Green Chile Quest"
      },
      "prompt": {
        "en": "Order something with green chile and take an epic photo of it."
      },
      "points": 10,
      "duration_minutes": 5
    },
    {
      "id": "university-area-task-10",
      "neighborhood_id": "university-area",
      "title": {
        "en": "Campus Pathways"
      },
      "prompt": {
        "en": "Take a photo of a tree-lined walkway or path on campus, focusing on the perspective."
      },
      "points": 10,
      "duration_minutes": 5
    },
    {
      "id": "university-area-task-11",
      "neighborhood_id": "university-area",
      "title": {
        "en": "Bookworm's View"
      },
      "prompt": {
        "en": "Take a photo that represents knowledge or learning, perhaps near a library or bookstore."
      },
      "points": 10,
      "duration_minutes": 5
    },
    {
      "id": "university-area-task-12",
      "neighborhood_id": "university-area",
      "title": {
        "en": "Timeless Classic"
      },
      "prompt": {
        "en": "Find a business that has been around for decades and take a photo of its classic sign or storefront."
      },
      "points": 10,
      "duration_minutes": 5
    },
    {
      "id": "university-area-task-13",
      "neighborhood_id": "university-area",
      "title": {
        "en": "Patio Season"
      },
      "prompt": {
        "en": "Find a sun-drenched patio and take a photo that makes you want to sit and relax."
      },
      "points": 10,
      "duration_minutes": 5
    },
    {
      "id": "university-area-task-14",
      "neighborhood_id": "university-area",
      "title": {
        "en": "Selfie with a Scholar"
      },
      "prompt": {
        "en": "Take a selfie in front of a statue or building named after a person on the UNM campus."
      },
      "points": 10,
      "duration_minutes": 5
    },
    {
      "id": "university-area-task-15",
      "neighborhood_id": "university-area",
      "title": {
        "en": "The Perfect Sopaipilla"
      },
      "prompt": {
        "en": "Find a sopaipilla and take a photo of it puffed up and drizzled with honey."
      },
      "points": 10,
      "duration_minutes": 5
    },
    {
      "id": "barelas-task-1",
      "neighborhood_id": "barelas",
      "title": {
        "en": "Echoes of the Railroad"
      },
      "prompt": {
        "en": "Find a visual reminder of the neighborhood's railroad history (tracks, old buildings, the Rail Yards) and take a dramatic photo."
      },
      "points": 10,
      "duration_minutes": 5
    },
    {
      "id": "barelas-task-2",
      "neighborhood_id": "barelas",
      "title": {
        "en": "Historic Adobe"
      },
      "prompt": {
        "en": "Photograph a generations-old adobe building, focusing on its texture and character."
      },
      "points": 10,
      "duration_minutes": 5
    },
    {
      "id": "barelas-task-3",
      "neighborhood_id": "barelas",
      "title": {
        "en": "Cultural Heart"
      },
      "prompt": {
        "en": "Take a photo that captures the Hispanic cultural pride of the neighborhood."
      },
      "points": 10,
      "duration_minutes": 5
    },
    {
      "id": "barelas-task-4",
      "neighborhood_id": "barelas",
      "title": {
        "en": "Legendary Food"
      },
      "prompt": {
        "en": "Get some food from a legendary local spot and take a portrait-style photo of it against the classic storefront."
      },
      "points": 10,
      "duration_minutes": 5
    },
    {
      "id": "barelas-task-5",
      "neighborhood_id": "barelas",
      "title": {
        "en": "Community Story"
      },
      "prompt": {
        "en": "Find a mural or a public sign that tells a story about the community's history or resilience."
      },
      "points": 10,
      "duration_minutes": 5
    },
    {
      "id": "barelas-task-6",
      "neighborhood_id": "barelas",
      "title": {
        "en": "Black and White History"
      },
      "prompt": {
        "en": "Take a photo of a historic building or street scene and edit it in black and white to emphasize the timeless quality."
      },
      "points": 10,
      "duration_minutes": 5
    },
    {
      "id": "barelas-task-7",
      "neighborhood_id": "barelas",
      "title": {
        "en": "A Taste of Tradition"
      },
      "prompt": {
        "en": "Photograph a food item that feels like it's been made the same way for generations, like a tamale."
      },
      "points": 10,
      "duration_minutes": 5
    },
    {
      "id": "barelas-task-8",
      "neighborhood_id": "barelas",
      "title": {
        "en": "Industrial Cathedral"
      },
      "prompt": {
        "en": "Take a photo of the Rail Yards that makes the industrial structures look grand and cathedral-like."
      },
      "points": 10,
      "duration_minutes": 5
    },
    {
      "id": "barelas-task-9",
      "neighborhood_id": "barelas",
      "title": {
        "en": "Fourth Street Stories"
      },
      "prompt": {
        "en": "Walk down South Fourth Street and take a photo of a storefront that looks like it has a long history."
      },
      "points": 10,
      "duration_minutes": 5
    },
    {
      "id": "barelas-task-10",
      "neighborhood_id": "barelas",
      "title": {
        "en": "Historical Marker"
      },
      "prompt": {
        "en": "Find and photograph a historical marker that explains a piece of the neighborhood's past."
      },
      "points": 10,
      "duration_minutes": 5
    },
    {
      "id": "barelas-task-11",
      "neighborhood_id": "barelas",
      "title": {
        "en": "Neighborhood Pride Selfie"
      },
      "prompt": {
        "en": "Take a selfie with a mural or sign that expresses the proud identity of Barelas."
      },
      "points": 10,
      "duration_minutes": 5
    },
    {
      "id": "barelas-task-12",
      "neighborhood_id": "barelas",
      "title": {
        "en": "The Waiting Game"
      },
      "prompt": {
        "en": "Capture the experience of waiting in line at a beloved local food spot, showing the devotion of the customers."
      },
      "points": 10,
      "duration_minutes": 5
    },
    {
      "id": "barelas-task-13",
      "neighborhood_id": "barelas",
      "title": {
        "en": "Art of Heritage"
      },
      "prompt": {
        "en": "Photograph a piece of art at the National Hispanic Cultural Center that speaks to you."
      },
      "points": 10,
      "duration_minutes": 5
    },
    {
      "id": "barelas-task-14",
      "neighborhood_id": "barelas",
      "title": {
        "en": "Sky over Barelas"
      },
      "prompt": {
        "en": "Take a wide shot that shows the big New Mexico sky over the historic low-rise buildings of the neighborhood."
      },
      "points": 10,
      "duration_minutes": 5
    },
    {
      "id": "barelas-task-15",
      "neighborhood_id": "barelas",
      "title": {
        "en": "Generations"
      },
      "prompt": {
        "en": "Find a scene that suggests the passing of time or the presence of multiple generations in the community."
      },
      "points": 10,
      "duration_minutes": 5
    },
    {
      "id": "international-district-task-1",
      "neighborhood_id": "international-district",
      "title": {
        "en": "Global Flavors"
      },
      "prompt": {
        "en": "Take a photo of a dish from a local restaurant that represents a specific global cuisine."
      },
      "points": 10,
      "duration_minutes": 5
    },
    {
      "id": "international-district-task-2",
      "neighborhood_id": "international-district",
      "title": {
        "en": "Mural Message"
      },
      "prompt": {
        "en": "Find a vibrant mural that depicts the culture of one of the communities in the district and capture its story."
      },
      "points": 10,
      "duration_minutes": 5
    },
    {
      "id": "international-district-task-3",
      "neighborhood_id": "international-district",
      "title": {
        "en": "Market Discovery"
      },
      "prompt": {
        "en": "Go into an international grocery store and take a photo of a product or ingredient you've never seen before."
      },
      "points": 10,
      "duration_minutes": 5
    },
    {
      "id": "international-district-task-4",
      "neighborhood_id": "international-district",
      "title": {
        "en": "Strip Mall Magic"
      },
      "prompt": {
        "en": "Take a photo that shows the unassuming exterior of a strip mall that hides a culinary gem inside."
      },
      "points": 10,
      "duration_minutes": 5
    },
    {
      "id": "international-district-task-5",
      "neighborhood_id": "international-district",
      "title": {
        "en": "Caffeine Kick"
      },
      "prompt": {
        "en": "Get a Vietnamese iced coffee and take a cool action shot of the condensed milk swirling into the coffee."
      },
      "points": 10,
      "duration_minutes": 5
    },
    {
      "id": "international-district-task-6",
      "neighborhood_id": "international-district",
      "title": {
        "en": "World on a Plate"
      },
      "prompt": {
        "en": "Create a flat-lay photo of your meal, showcasing the colors and variety of the food."
      },
      "points": 10,
      "duration_minutes": 5
    },
    {
      "id": "international-district-task-7",
      "neighborhood_id": "international-district",
      "title": {
        "en": "Signs of the World"
      },
      "prompt": {
        "en": "Find a sign written in a language other than English and take a picture of it."
      },
      "points": 10,
      "duration_minutes": 5
    },
    {
      "id": "international-district-task-8",
      "neighborhood_id": "international-district",
      "title": {
        "en": "The Perfect Bánh Mì"
      },
      "prompt": {
        "en": "Take a close-up photo of a bánh mì sandwich that highlights its crispy baguette and fresh ingredients."
      },
      "points": 10,
      "duration_minutes": 5
    },
    {
      "id": "international-district-task-9",
      "neighborhood_id": "international-district",
      "title": {
        "en": "Neighborhood Fabric"
      },
      "prompt": {
        "en": "Take a photo that captures the diversity of the people and cultures in the neighborhood."
      },
      "points": 10,
      "duration_minutes": 5
    },
    {
      "id": "international-district-task-10",
      "neighborhood_id": "international-district",
      "title": {
        "en": "Unpretentious Gem"
      },
      "prompt": {
        "en": "Photograph a restaurant or shop that looks simple on the outside but is known for being amazing."
      },
      "points": 10,
      "duration_minutes": 5
    },
    {
      "id": "international-district-task-11",
      "neighborhood_id": "international-district",
      "title": {
        "en": "Colorful Aisles"
      },
      "prompt": {
        "en": "Capture the vibrant colors of the produce or snack aisles in an international market."
      },
      "points": 10,
      "duration_minutes": 5
    },
    {
      "id": "international-district-task-12",
      "neighborhood_id": "international-district",
      "title": {
        "en": "Fairgrounds Find"
      },
      "prompt": {
        "en": "Explore the edge of the Expo New Mexico grounds and find a quirky statue or piece of architecture to photograph."
      },
      "points": 10,
      "duration_minutes": 5
    },
    {
      "id": "international-district-task-13",
      "neighborhood_id": "international-district",
      "title": {
        "en": "Global Selfie"
      },
      "prompt": {
        "en": "Take a selfie in front of a mural or restaurant that represents a country you'd love to visit."
      },
      "points": 10,
      "duration_minutes": 5
    },
    {
      "id": "international-district-task-14",
      "neighborhood_id": "international-district",
      "title": {
        "en": "Sweet Treat"
      },
      "prompt": {
        "en": "Buy a pastry from a bakery you've never tried before and take a picture of it."
      },
      "points": 10,
      "duration_minutes": 5
    },
    {
      "id": "international-district-task-15",
      "neighborhood_id": "international-district",
      "title": {
        "en": "Central Artery"
      },
      "prompt": {
        "en": "Take a photo down Central Avenue that shows the mix of businesses and the constant flow of life in the district."
      },
      "points": 10,
      "duration_minutes": 5
    },
    {
      "id": "old-town-sawmill-task-1",
      "neighborhood_id": "old-town-sawmill",
      "title": {
        "en": "Adobe & Shadows"
      },
      "prompt": {
        "en": "Find a quiet courtyard or backstreet and take a photo that plays with the strong sunlight and shadows on the adobe walls."
      },
      "points": 10,
      "duration_minutes": 5
    },
    {
      "id": "old-town-sawmill-task-2",
      "neighborhood_id": "old-town-sawmill",
      "title": {
        "en": "Historic to Modern"
      },
      "prompt": {
        "en": "Capture a single image that shows the contrast between the historic adobe of Old Town and the industrial chic of the Sawmill district."
      },
      "points": 10,
      "duration_minutes": 5
    },
    {
      "id": "old-town-sawmill-task-3",
      "neighborhood_id": "old-town-sawmill",
      "title": {
        "en": "Hidden Courtyard"
      },
      "prompt": {
        "en": "Duck off the main plaza to find a hidden placita or courtyard and take a photo of its peaceful atmosphere."
      },
      "points": 10,
      "duration_minutes": 5
    },
    {
      "id": "old-town-sawmill-task-4",
      "neighborhood_id": "old-town-sawmill",
      "title": {
        "en": "Colorful Door"
      },
      "prompt": {
        "en": "Wander the residential backstreets and find a beautifully colored door or gate to photograph."
      },
      "points": 10,
      "duration_minutes": 5
    },
    {
      "id": "old-town-sawmill-task-5",
      "neighborhood_id": "old-town-sawmill",
      "title": {
        "en": "Industrial Energy"
      },
      "prompt": {
        "en": "Take a photo inside or around Sawmill Market that captures its bustling, modern, industrial vibe."
      },
      "points": 10,
      "duration_minutes": 5
    },
    {
      "id": "old-town-sawmill-task-6",
      "neighborhood_id": "old-town-sawmill",
      "title": {
        "en": "Artisan's Craft"
      },
      "prompt": {
        "en": "Find a piece of local art or craft in a shop window and take a close-up photo of the details."
      },
      "points": 10,
      "duration_minutes": 5
    },
    {
      "id": "old-town-sawmill-task-7",
      "neighborhood_id": "old-town-sawmill",
      "title": {
        "en": "Chile Ristra"
      },
      "prompt": {
        "en": "Find a string of red chile ristras hanging from an adobe wall and take a classic New Mexico photo."
      },
      "points": 10,
      "duration_minutes": 5
    },
    {
      "id": "old-town-sawmill-task-8",
      "neighborhood_id": "old-town-sawmill",
      "title": {
        "en": "Indigenous Cuisine"
      },
      "prompt": {
        "en": "Photograph a dish made with traditional Indigenous ingredients, highlighting its artistry and connection to the land."
      },
      "points": 10,
      "duration_minutes": 5
    },
    {
      "id": "old-town-sawmill-task-9",
      "neighborhood_id": "old-town-sawmill",
      "title": {
        "en": "Secret Garden"
      },
      "prompt": {
        "en": "Discover a small garden or fountain hidden away in a courtyard and capture its charm."
      },
      "points": 10,
      "duration_minutes": 5
    },
    {
      "id": "old-town-sawmill-task-10",
      "neighborhood_id": "old-town-sawmill",
      "title": {
        "en": "Food Hall Feast"
      },
      "prompt": {
        "en": "Take a photo that shows the variety and energy of the food vendors at Sawmill Market."
      },
      "points": 10,
      "duration_minutes": 5
    },
    {
      "id": "old-town-sawmill-task-11",
      "neighborhood_id": "old-town-sawmill",
      "title": {
        "en": "Historic Selfie"
      },
      "prompt": {
        "en": "Take a selfie in front of the San Felipe de Neri Church, the historic anchor of Old Town."
      },
      "points": 10,
      "duration_minutes": 5
    },
    {
      "id": "old-town-sawmill-task-12",
      "neighborhood_id": "old-town-sawmill",
      "title": {
        "en": "Local's Haven"
      },
      "prompt": {
        "en": "Find a quiet cafe or grocer away from the main tourist crowds and take a photo of your peaceful moment."
      },
      "points": 10,
      "duration_minutes": 5
    },
    {
      "id": "old-town-sawmill-task-13",
      "neighborhood_id": "old-town-sawmill",
      "title": {
        "en": "Texture Study"
      },
      "prompt": {
        "en": "Get very close to an old adobe wall and take a photo that is all about the texture of the sun-baked earth."
      },
      "points": 10,
      "duration_minutes": 5
    },
    {
      "id": "old-town-sawmill-task-14",
      "neighborhood_id": "old-town-sawmill",
      "title": {
        "en": "People Watching"
      },
      "prompt": {
        "en": "Find a bench and take a candid photo that captures the mix of locals and tourists exploring the area."
      },
      "points": 10,
      "duration_minutes": 5
    },
    {
      "id": "old-town-sawmill-task-15",
      "neighborhood_id": "old-town-sawmill",
      "title": {
        "en": "From Past to Present"
      },
      "prompt": {
        "en": "Take a photo of your feet, one in a historic part of Old Town and one in the modern Sawmill Market, showing your journey."
      },
      "points": 10,
      "duration_minutes": 5
    }
  ]
}