{
  "neighborhoods": [
    {
      "id": "hampden",
      "city_id": "baltimore",
      "name": {
        "en": "Hampden"
      },
      "summary": {
        "en": "Quirky, independent, and effortlessly cool. Hampden is a neighborhood of unexpected discoveries, where vintage charm collides with a fiercely independent, modern spirit."
      },
      "lat": 39.3325,
      "lng": -76.632,
      "trending_score": 85
    },
    {
      "id": "old-goucher",
      "city_id": "baltimore",
      "name": {
        "en": "Old Goucher"
      },
      "summary": {
        "en": "Secretive, sophisticated, and intimate. This neighborhood is for those who love the thrill of discovery, with the best spots tucked away in historic buildings."
      },
      "lat": 39.3155,
      "lng": -76.6172,
      "trending_score": 90
    },
    {
      "id": "station-north",
      "city_id": "baltimore",
      "name": {
        "en": "Station North Arts & Entertainment District"
      },
      "summary": {
        "en": "Artsy, edgy, and cinematic. This is Baltimore's creative heart, where historic buildings house indie theaters, music venues, and bars that feel straight out of a film noir."
      },
      "lat": 39.309,
      "lng": -76.6175,
      "trending_score": 88
    },
    {
      "id": "fells-point",
      "city_id": "baltimore",
      "name": {
        "en": "Fell's Point"
      },
      "summary": {
        "en": "Historic, maritime, and spirited. With its authentic cobblestone streets and a legacy of Irish immigrants, this neighborhood feels like a step back in time."
      },
      "lat": 39.2815,
      "lng": -76.595,
      "trending_score": 92
    },
    {
      "id": "charles-village-waverly",
      "city_id": "baltimore",
      "name": {
        "en": "Charles Village & Waverly"
      },
      "summary": {
        "en": "Academic, cultural, and unpretentiously cool. This area has a relaxed, intellectual energy that extends to its unique restaurants and proud local breweries."
      },
      "lat": 39.328,
      "lng": -76.617,
      "trending_score": 80
    },
    {
      "id": "mount-vernon-downtown",
      "city_id": "baltimore",
      "name": {
        "en": "Mount Vernon & Downtown Core"
      },
      "summary": {
        "en": "Elegant, historic, and full of hidden culinary treasures. Grand 19th-century architecture blends with unassuming storefronts hiding ambitious food experiences."
      },
      "lat": 39.2975,
      "lng": -76.6155,
      "trending_score": 89
    }
  ],
  "waypoints": [
    {
      "id": "hampden-rocket-to-venus",
      "city_id": "baltimore",
      "neighborhood_id": "hampden",
      "name": {
        "en": "Rocket To Venus"
      },
      "description": {
        "en": "A beloved neighborhood bar instantly recognizable by the iconic space-age missile sculpture on its exterior, with a laid-back, unpretentious atmosphere."
      },
      "type": "drink",
      "lat": 39.3328,
      "lng": -76.6322,
      "trending_score": 85
    },
    {
      "id": "hampden-melanies-at-griffiths-tavern",
      "city_id": "baltimore",
      "neighborhood_id": "hampden",
      "name": {
        "en": "Melanie’s at Griffith’s Tavern"
      },
      "description": {
        "en": "A century-old tavern given new life, this spot perfectly executes the modern dive bar aesthetic with fresh neon signs and expertly crafted cocktails."
      },
      "type": "drink",
      "lat": 39.3321,
      "lng": -76.6315,
      "trending_score": 82
    },
    {
      "id": "hampden-the-duchess",
      "city_id": "baltimore",
      "neighborhood_id": "hampden",
      "name": {
        "en": "The Duchess"
      },
      "description": {
        "en": "A wonderfully unique spot that is a British pub, a folk music venue, and a Chamorran restaurant serving cuisine from Guam."
      },
      "type": "food",
      "lat": 39.3326,
      "lng": -76.6331,
      "trending_score": 88
    },
    {
      "id": "hampden-ekiben",
      "city_id": "baltimore",
      "neighborhood_id": "hampden",
      "name": {
        "en": "Ekiben"
      },
      "description": {
        "en": "A must-visit for casual, inventive Asian-fusion, famous for its steamed bun sandwiches that locals crave and recommend."
      },
      "type": "food",
      "lat": 39.3329,
      "lng": -76.6345,
      "trending_score": 95
    },
    {
      "id": "hampden-dylans-oyster-cellar",
      "city_id": "baltimore",
      "neighborhood_id": "hampden",
      "name": {
        "en": "Dylan's Oyster Cellar"
      },
      "description": {
        "en": "Widely considered the best place in Baltimore to eat oysters, this is the definitive neighborhood seafood joint in a relaxed setting."
      },
      "type": "food",
      "lat": 39.3333,
      "lng": -76.635,
      "trending_score": 91
    },
    {
      "id": "hampden-rocket-sculpture",
      "city_id": "baltimore",
      "neighborhood_id": "hampden",
      "name": {
        "en": "The Rocket Sculpture"
      },
      "description": {
        "en": "More than just a sign, this missile at Rocket To Venus is a piece of public art and a neighborhood landmark that captures Hampden's offbeat spirit."
      },
      "type": "landmark",
      "lat": 39.3328,
      "lng": -76.6323,
      "trending_score": 80
    },
    {
      "id": "old-goucher-fadensonnen",
      "city_id": "baltimore",
      "neighborhood_id": "old-goucher",
      "name": {
        "en": "Fadensonnen"
      },
      "description": {
        "en": "A candle-lit sake and natural wine bar hidden from the street. Finding this atmospheric gem through a gate and courtyard is a true urban adventure."
      },
      "type": "hidden_gem",
      "lat": 39.3152,
      "lng": -76.617,
      "trending_score": 94
    },
    {
      "id": "old-goucher-dutch-courage",
      "city_id": "baltimore",
      "neighborhood_id": "old-goucher",
      "name": {
        "en": "Dutch Courage"
      },
      "description": {
        "en": "A veritable library of gin and home to some of the city's best bartenders, with a sophisticated atmosphere perfect for a pre-dinner G&T."
      },
      "type": "drink",
      "lat": 39.316,
      "lng": -76.6178,
      "trending_score": 90
    },
    {
      "id": "old-goucher-mama-kokos",
      "city_id": "baltimore",
      "neighborhood_id": "old-goucher",
      "name": {
        "en": "Mama Koko’s"
      },
      "description": {
        "en": "Located in a meticulously renovated 133-year-old historic mansion, this bar is hard to classify but easy to love for its stunning setting."
      },
      "type": "drink",
      "lat": 39.3148,
      "lng": -76.6165,
      "trending_score": 87
    },
    {
      "id": "old-goucher-clavel",
      "city_id": "baltimore",
      "neighborhood_id": "old-goucher",
      "name": {
        "en": "Clavel"
      },
      "description": {
        "en": "The epicenter of Baltimore's food buzz, this celebrated Mexican restaurant and Maryland's first mezcaleria is worth the line."
      },
      "type": "food",
      "lat": 39.3175,
      "lng": -76.6145,
      "trending_score": 98
    },
    {
      "id": "old-goucher-fadensonnen-courtyard",
      "city_id": "baltimore",
      "neighborhood_id": "old-goucher",
      "name": {
        "en": "Fadensonnen's Hidden Courtyard"
      },
      "description": {
        "en": "The entrance to the bar creates a transportive buffer from the city, making it feel like a secret garden and a true escape."
      },
      "type": "landmark",
      "lat": 39.3151,
      "lng": -76.6171,
      "trending_score": 85
    },
    {
      "id": "station-north-the-royal-blue",
      "city_id": "baltimore",
      "neighborhood_id": "station-north",
      "name": {
        "en": "The Royal Blue"
      },
      "description": {
        "en": "An all-day, all-purpose bar that hits the sweet spot for any occasion. It’s a stylish and reliable neighborhood hub."
      },
      "type": "drink",
      "lat": 39.3095,
      "lng": -76.6176,
      "trending_score": 86
    },
    {
      "id": "station-north-club-charles",
      "city_id": "baltimore",
      "neighborhood_id": "station-north",
      "name": {
        "en": "Club Charles"
      },
      "description": {
        "en": "A classic dive bar with an art deco flair, marked only by a glowing neon 'cocktails' sign, making it feel like a secret hideout."
      },
      "type": "nightlife",
      "lat": 39.3088,
      "lng": -76.6174,
      "trending_score": 89
    },
    {
      "id": "station-north-alma-cocina-latina",
      "city_id": "baltimore",
      "neighborhood_id": "station-north",
      "name": {
        "en": "Alma Cocina Latina"
      },
      "description": {
        "en": "A vibrant Venezuelan spot that is a haven for happy hour, perfect for starting an evening with expertly crafted cocktails and arepas."
      },
      "type": "food",
      "lat": 39.3085,
      "lng": -76.6173,
      "trending_score": 90
    },
    {
      "id": "station-north-cocktails-neon-sign",
      "city_id": "baltimore",
      "neighborhood_id": "station-north",
      "name": {
        "en": "The 'Cocktails' Neon Sign"
      },
      "description": {
        "en": "This iconic, minimalist sign at Club Charles is a neighborhood landmark, casting a moody, cinematic glow onto the street."
      },
      "type": "landmark",
      "lat": 39.3089,
      "lng": -76.6175,
      "trending_score": 84
    },
    {
      "id": "station-north-neighborhood-murals",
      "city_id": "baltimore",
      "neighborhood_id": "station-north",
      "name": {
        "en": "Neighborhood Murals"
      },
      "description": {
        "en": "As an official Arts & Entertainment District, the walls of the old industrial buildings serve as a public canvas for large-scale murals."
      },
      "type": "culture",
      "lat": 39.3105,
      "lng": -76.6168,
      "trending_score": 80
    },
    {
      "id": "station-north-ottobar",
      "city_id": "baltimore",
      "neighborhood_id": "station-north",
      "name": {
        "en": "Ottobar"
      },
      "description": {
        "en": "A legendary venue for indie, punk, and metal shows. The upstairs bar is often open without a cover for a taste of the local music scene."
      },
      "type": "nightlife",
      "lat": 39.3185,
      "lng": -76.6195,
      "trending_score": 88
    },
    {
      "id": "fells-point-the-wren",
      "city_id": "baltimore",
      "neighborhood_id": "fells-point",
      "name": {
        "en": "The Wren"
      },
      "description": {
        "en": "An Irish pub that feels genuinely historic, like a place your 'great grandparents might have hunched over a pint.' It's cozy and authentic."
      },
      "type": "drink",
      "lat": 39.282,
      "lng": -76.5945,
      "trending_score": 85
    },
    {
      "id": "fells-point-hudson-street-stack-house",
      "city_id": "baltimore",
      "neighborhood_id": "fells-point",
      "name": {
        "en": "Hudson Street Stack House"
      },
      "description": {
        "en": "A crowd-pleasing bar on the border of Fell's Point and Canton, known for its welcoming vibe and solid drinks list."
      },
      "type": "drink",
      "lat": 39.2801,
      "lng": -76.5825,
      "trending_score": 80
    },
    {
      "id": "fells-point-bunnys-buckets-bubbles",
      "city_id": "baltimore",
      "neighborhood_id": "fells-point",
      "name": {
        "en": "Bunny’s Buckets & Bubbles"
      },
      "description": {
        "en": "This spot perfects the high-low experience, offering an unexpected but brilliant pairing of champagne and caviar in a relaxed setting."
      },
      "type": "food",
      "lat": 39.2818,
      "lng": -76.596,
      "trending_score": 88
    },
    {
      "id": "fells-point-cobblestone-streets",
      "city_id": "baltimore",
      "neighborhood_id": "fells-point",
      "name": {
        "en": "The Cobblestone Streets"
      },
      "description": {
        "en": "The most defining feature of the neighborhood. Wander down Thames Street or Shakespeare Street and feel the history under your feet."
      },
      "type": "landmark",
      "lat": 39.2812,
      "lng": -76.5955,
      "trending_score": 90
    },
    {
      "id": "fells-point-historic-waterfront",
      "city_id": "baltimore",
      "neighborhood_id": "fells-point",
      "name": {
        "en": "Historic Waterfront"
      },
      "description": {
        "en": "Stroll along the harbor to see the tugboats and water taxis. The view of the water against the 19th-century architecture is quintessential Baltimore."
      },
      "type": "viewpoint",
      "lat": 39.2805,
      "lng": -76.597,
      "trending_score": 92
    },
    {
      "id": "charles-village-waverly-peabody-heights",
      "city_id": "baltimore",
      "neighborhood_id": "charles-village-waverly",
      "name": {
        "en": "Peabody Heights"
      },
      "description": {
        "en": "A craft brewery that 'screams Baltimore pride.' It's a spacious, friendly spot to sample local beers and feel the authentic spirit of the city."
      },
      "type": "drink",
      "lat": 39.3225,
      "lng": -76.608,
      "trending_score": 87
    },
    {
      "id": "charles-village-waverly-gertrudes-chesapeake-kitchen",
      "city_id": "baltimore",
      "neighborhood_id": "charles-village-waverly",
      "name": {
        "en": "Gertrude’s Chesapeake Kitchen"
      },
      "description": {
        "en": "Located inside the Baltimore Museum of Art, this is one of the best places to sample seafood from the Chesapeake Bay in an elegant setting."
      },
      "type": "food",
      "lat": 39.3275,
      "lng": -76.619,
      "trending_score": 90
    },
    {
      "id": "charles-village-waverly-toki-underground",
      "city_id": "baltimore",
      "neighborhood_id": "charles-village-waverly",
      "name": {
        "en": "Toki Underground"
      },
      "description": {
        "en": "Step through an unassuming exterior into what feels like an intimate Tokyo speakeasy for a transportive and delicious ramen experience."
      },
      "type": "hidden_gem",
      "lat": 39.3255,
      "lng": -76.6175,
      "trending_score": 93
    },
    {
      "id": "charles-village-waverly-baltimore-museum-of-art",
      "city_id": "baltimore",
      "neighborhood_id": "charles-village-waverly",
      "name": {
        "en": "Baltimore Museum of Art (BMA)"
      },
      "description": {
        "en": "A world-class museum that is completely free to enter. It's a cultural landmark and a perfect stop for art lovers."
      },
      "type": "culture",
      "lat": 39.3278,
      "lng": -76.6188,
      "trending_score": 91
    },
    {
      "id": "mount-vernon-downtown-blooms",
      "city_id": "baltimore",
      "neighborhood_id": "mount-vernon-downtown",
      "name": {
        "en": "Bloom’s"
      },
      "description": {
        "en": "A stylish and moody cocktail bar located inside the Hotel Ulysses. The atmosphere is electric, promising a great night."
      },
      "type": "nightlife",
      "lat": 39.2955,
      "lng": -76.616,
      "trending_score": 92
    },
    {
      "id": "mount-vernon-downtown-puerto-511",
      "city_id": "baltimore",
      "neighborhood_id": "mount-vernon-downtown",
      "name": {
        "en": "Puerto 511 Cocina Peruana"
      },
      "description": {
        "en": "A special occasion Peruvian tasting menu spot that is 'a little hard to find' but well worth the search for the dedicated foodie."
      },
      "type": "hidden_gem",
      "lat": 39.294,
      "lng": -76.6165,
      "trending_score": 95
    },
    {
      "id": "mount-vernon-downtown-faidleys-seafood",
      "city_id": "baltimore",
      "neighborhood_id": "mount-vernon-downtown",
      "name": {
        "en": "Faidley's Seafood"
      },
      "description": {
        "en": "A legendary institution within Lexington Market, it's an essential, non-touristy experience for tasting one of Baltimore's best crab cakes."
      },
      "type": "food",
      "lat": 39.2908,
      "lng": -76.622,
      "trending_score": 97
    },
    {
      "id": "mount-vernon-downtown-hotel-ulysses",
      "city_id": "baltimore",
      "neighborhood_id": "mount-vernon-downtown",
      "name": {
        "en": "The Hotel Ulysses"
      },
      "description": {
        "en": "Home of Bloom's bar, this beautifully restored historic building is worth appreciating as an example of Mount Vernon's Gilded Age grandeur."
      },
      "type": "landmark",
      "lat": 39.2956,
      "lng": -76.6161,
      "trending_score": 85
    },
    {
      "id": "mount-vernon-downtown-lexington-market",
      "city_id": "baltimore",
      "neighborhood_id": "mount-vernon-downtown",
      "name": {
        "en": "Lexington Market"
      },
      "description": {
        "en": "While Faidley's is the star, the market itself is a historic landmark providing a vibrant, sensory slice of authentic Baltimore life."
      },
      "type": "culture",
      "lat": 39.291,
      "lng": -76.6218,
      "trending_score": 88
    }
  ],
  "tasks": [
    {
      "id": "hampden-task-1",
      "neighborhood_id": "hampden",
      "title": {
        "en": "Quirky Detail"
      },
      "prompt": {
        "en": "Find the most unusual or quirky piece of decoration on a building's facade and take a close-up shot."
      },
      "points": 10,
      "duration_minutes": 5
    },
    {
      "id": "hampden-task-2",
      "neighborhood_id": "hampden",
      "title": {
        "en": "Vintage Vibes"
      },
      "prompt": {
        "en": "Capture a photo that perfectly encapsulates Hampden's vintage charm. Look for old signs, classic storefronts, or retro fashion."
      },
      "points": 10,
      "duration_minutes": 5
    },
    {
      "id": "hampden-task-3",
      "neighborhood_id": "hampden",
      "title": {
        "en": "Independent Spirit"
      },
      "prompt": {
        "en": "Take a picture of a storefront or sign that screams 'fiercely independent.' What makes it unique?"
      },
      "points": 10,
      "duration_minutes": 5
    },
    {
      "id": "hampden-task-4",
      "neighborhood_id": "hampden",
      "title": {
        "en": "Effortlessly Cool Selfie"
      },
      "prompt": {
        "en": "Find a backdrop that feels effortlessly cool and take a selfie. Bonus points for a relaxed, unpretentious pose."
      },
      "points": 10,
      "duration_minutes": 5
    },
    {
      "id": "hampden-task-5",
      "neighborhood_id": "hampden",
      "title": {
        "en": "Unexpected Discovery"
      },
      "prompt": {
        "en": "Photograph something you genuinely did not expect to find in this neighborhood. A strange sculpture, a hidden alley, a weird window display."
      },
      "points": 10,
      "duration_minutes": 5
    },
    {
      "id": "hampden-task-6",
      "neighborhood_id": "hampden",
      "title": {
        "en": "Local Flavor"
      },
      "prompt": {
        "en": "Capture a photo of a food or drink item that feels uniquely 'Hampden.' It could be from a local cafe, bar, or restaurant."
      },
      "points": 10,
      "duration_minutes": 5
    },
    {
      "id": "hampden-task-7",
      "neighborhood_id": "hampden",
      "title": {
        "en": "Color Collision"
      },
      "prompt": {
        "en": "Find a spot where two bold, contrasting colors meet on a building or mural. Frame a shot that highlights this collision."
      },
      "points": 10,
      "duration_minutes": 5
    },
    {
      "id": "hampden-task-8",
      "neighborhood_id": "hampden",
      "title": {
        "en": "The Perfect Hangout Spot"
      },
      "prompt": {
        "en": "Take a photo of a bench, stoop, or outdoor seating area that looks like the perfect place for a local to hang out."
      },
      "points": 10,
      "duration_minutes": 5
    },
    {
      "id": "hampden-task-9",
      "neighborhood_id": "hampden",
      "title": {
        "en": "Modern Meets Historic"
      },
      "prompt": {
        "en": "Find an example of a modern design element (like a new sign or sculpture) on a classic, old building and capture it in a single photo."
      },
      "points": 10,
      "duration_minutes": 5
    },
    {
      "id": "hampden-task-10",
      "neighborhood_id": "hampden",
      "title": {
        "en": "Neighborhood Texture"
      },
      "prompt": {
        "en": "Get up close and personal with the neighborhood. Take a macro shot of an interesting texture you find, like peeling paint, old brick, or a mosaic."
      },
      "points": 10,
      "duration_minutes": 5
    },
    {
      "id": "hampden-task-11",
      "neighborhood_id": "hampden",
      "title": {
        "en": "Window Shopping"
      },
      "prompt": {
        "en": "Photograph the most creative or bizarre window display you can find in one of the independent shops."
      },
      "points": 10,
      "duration_minutes": 5
    },
    {
      "id": "hampden-task-12",
      "neighborhood_id": "hampden",
      "title": {
        "en": "Street Style"
      },
      "prompt": {
        "en": "Discreetly capture a photo that represents the unique fashion sense of the neighborhood's locals."
      },
      "points": 10,
      "duration_minutes": 5
    },
    {
      "id": "hampden-task-13",
      "neighborhood_id": "hampden",
      "title": {
        "en": "A Sign of the Times"
      },
      "prompt": {
        "en": "Find a handmade or hand-painted sign and take a picture of it. What does it say about the local culture?"
      },
      "points": 10,
      "duration_minutes": 5
    },
    {
      "id": "hampden-task-14",
      "neighborhood_id": "hampden",
      "title": {
        "en": "The Unofficial Mascot"
      },
      "prompt": {
        "en": "Find an animal (real or statue) that could be the unofficial mascot of Hampden. A pink flamingo, a quirky dog, etc. Snap a pic!"
      },
      "points": 10,
      "duration_minutes": 5
    },
    {
      "id": "hampden-task-15",
      "neighborhood_id": "hampden",
      "title": {
        "en": "Offbeat Art"
      },
      "prompt": {
        "en": "Photograph a piece of public art that isn't a mural or a formal statue. Look for art in unexpected places."
      },
      "points": 10,
      "duration_minutes": 5
    },
    {
      "id": "old-goucher-task-1",
      "neighborhood_id": "old-goucher",
      "title": {
        "en": "Secretive Entrance"
      },
      "prompt": {
        "en": "Find a doorway, gate, or alley that looks like it leads to a secret spot. Take a photo that enhances its mystery."
      },
      "points": 10,
      "duration_minutes": 5
    },
    {
      "id": "old-goucher-task-2",
      "neighborhood_id": "old-goucher",
      "title": {
        "en": "Candle-lit Selfie"
      },
      "prompt": {
        "en": "Find a spot with warm, low lighting (like a bar interior or a streetlamp's glow) and take a moody, atmospheric selfie."
      },
      "points": 10,
      "duration_minutes": 5
    },
    {
      "id": "old-goucher-task-3",
      "neighborhood_id": "old-goucher",
      "title": {
        "en": "Architectural Elegance"
      },
      "prompt": {
        "en": "Capture a sophisticated architectural detail on one of the historic buildings—an ornate window, a carved stone element, or an elegant iron fence."
      },
      "points": 10,
      "duration_minutes": 5
    },
    {
      "id": "old-goucher-task-4",
      "neighborhood_id": "old-goucher",
      "title": {
        "en": "The Thrill of Discovery"
      },
      "prompt": {
        "en": "Photograph a detail that most people would probably walk right past without noticing. A tiny plaque, a hidden garden, a unique doorknob."
      },
      "points": 10,
      "duration_minutes": 5
    },
    {
      "id": "old-goucher-task-5",
      "neighborhood_id": "old-goucher",
      "title": {
        "en": "Intimate Corner"
      },
      "prompt": {
        "en": "Find a quiet, intimate-feeling corner of the neighborhood and take a photo that captures its peaceful atmosphere."
      },
      "points": 10,
      "duration_minutes": 5
    },
    {
      "id": "old-goucher-task-6",
      "neighborhood_id": "old-goucher",
      "title": {
        "en": "Shadow and Light"
      },
      "prompt": {
        "en": "Play with the light. Take a photo that focuses on the dramatic interplay between shadows and light on a building or street."
      },
      "points": 10,
      "duration_minutes": 5
    },
    {
      "id": "old-goucher-task-7",
      "neighborhood_id": "old-goucher",
      "title": {
        "en": "A World-Class Drink"
      },
      "prompt": {
        "en": "Order a beautifully crafted cocktail or drink and take an artistic photo of it before you take a sip."
      },
      "points": 10,
      "duration_minutes": 5
    },
    {
      "id": "old-goucher-task-8",
      "neighborhood_id": "old-goucher",
      "title": {
        "en": "Unmarked Charm"
      },
      "prompt": {
        "en": "Find a beautiful building that has no obvious sign indicating what it is. Capture its mysterious charm."
      },
      "points": 10,
      "duration_minutes": 5
    },
    {
      "id": "old-goucher-task-9",
      "neighborhood_id": "old-goucher",
      "title": {
        "en": "Historic Reflection"
      },
      "prompt": {
        "en": "Find a reflection of a historic building in a modern window or a puddle. Capture both the old and new in one shot."
      },
      "points": 10,
      "duration_minutes": 5
    },
    {
      "id": "old-goucher-task-10",
      "neighborhood_id": "old-goucher",
      "title": {
        "en": "The Quiet Street"
      },
      "prompt": {
        "en": "Take a photo down a quiet side street that feels like a hidden escape from the main city buzz."
      },
      "points": 10,
      "duration_minutes": 5
    },
    {
      "id": "old-goucher-task-11",
      "neighborhood_id": "old-goucher",
      "title": {
        "en": "Sophisticated Still Life"
      },
      "prompt": {
        "en": "Create a still life photo using items on your table at a cafe or bar. Think elegant glassware, a menu, a single flower."
      },
      "points": 10,
      "duration_minutes": 5
    },
    {
      "id": "old-goucher-task-12",
      "neighborhood_id": "old-goucher",
      "title": {
        "en": "Living History"
      },
      "prompt": {
        "en": "Photograph a detail that shows the age of a building, like worn steps, weathered brick, or an old-fashioned gas lamp."
      },
      "points": 10,
      "duration_minutes": 5
    },
    {
      "id": "old-goucher-task-13",
      "neighborhood_id": "old-goucher",
      "title": {
        "en": "Up the Backstairs"
      },
      "prompt": {
        "en": "Find an interesting staircase, either exterior or interior, and take a photo from a low angle looking up."
      },
      "points": 10,
      "duration_minutes": 5
    },
    {
      "id": "old-goucher-task-14",
      "neighborhood_id": "old-goucher",
      "title": {
        "en": "Courtyard Calm"
      },
      "prompt": {
        "en": "Discover a hidden courtyard or small garden space and capture its tranquil atmosphere."
      },
      "points": 10,
      "duration_minutes": 5
    },
    {
      "id": "old-goucher-task-15",
      "neighborhood_id": "old-goucher",
      "title": {
        "en": "Explorer's Reward"
      },
      "prompt": {
        "en": "Take a selfie at the end of a hidden alley or inside a hard-to-find spot, looking proud of your discovery."
      },
      "points": 10,
      "duration_minutes": 5
    },
    {
      "id": "station-north-task-1",
      "neighborhood_id": "station-north",
      "title": {
        "en": "Cinematic Street Scene"
      },
      "prompt": {
        "en": "Frame a shot of a street corner or alley that looks like a still from a movie. Pay attention to lighting and mood."
      },
      "points": 10,
      "duration_minutes": 5
    },
    {
      "id": "station-north-task-2",
      "neighborhood_id": "station-north",
      "title": {
        "en": "Mural Selfie"
      },
      "prompt": {
        "en": "Find your favorite piece of street art or a mural and take a creative selfie with it. Try to interact with the art in your pose."
      },
      "points": 10,
      "duration_minutes": 5
    },
    {
      "id": "station-north-task-3",
      "neighborhood_id": "station-north",
      "title": {
        "en": "Neon Noir"
      },
      "prompt": {
        "en": "Capture the glow of a neon sign reflecting on a wet street or a window. The moodier, the better."
      },
      "points": 10,
      "duration_minutes": 5
    },
    {
      "id": "station-north-task-4",
      "neighborhood_id": "station-north",
      "title": {
        "en": "Creative Energy"
      },
      "prompt": {
        "en": "Take a photo that you feel captures the 'creative heart' of the neighborhood. It could be a person, a place, or an object."
      },
      "points": 10,
      "duration_minutes": 5
    },
    {
      "id": "station-north-task-5",
      "neighborhood_id": "station-north",
      "title": {
        "en": "Industrial Texture"
      },
      "prompt": {
        "en": "Get a close-up shot of the textures of an old industrial building: rust, brick, corrugated metal, or peeling paint."
      },
      "points": 10,
      "duration_minutes": 5
    },
    {
      "id": "station-north-task-6",
      "neighborhood_id": "station-north",
      "title": {
        "en": "After-Dark Vibe"
      },
      "prompt": {
        "en": "As evening approaches, take a photo that captures the neighborhood's after-dark energy. Focus on lights, shadows, and movement."
      },
      "points": 10,
      "duration_minutes": 5
    },
    {
      "id": "station-north-task-7",
      "neighborhood_id": "station-north",
      "title": {
        "en": "Art in Unexpected Places"
      },
      "prompt": {
        "en": "Find a piece of art that isn't a huge mural. Look for stickers, small stencils, or sculptures in unusual spots."
      },
      "points": 10,
      "duration_minutes": 5
    },
    {
      "id": "station-north-task-8",
      "neighborhood_id": "station-north",
      "title": {
        "en": "The All-Day Hub"
      },
      "prompt": {
        "en": "Photograph a place that looks like it could be busy from morning coffee to late-night cocktails. What clues tell you this?"
      },
      "points": 10,
      "duration_minutes": 5
    },
    {
      "id": "station-north-task-9",
      "neighborhood_id": "station-north",
      "title": {
        "en": "Edgy Portrait"
      },
      "prompt": {
        "en": "Use a gritty, artistic backdrop like a graffiti-covered wall or an old fire escape for a cool portrait of yourself or a friend."
      },
      "points": 10,
      "duration_minutes": 5
    },
    {
      "id": "station-north-task-10",
      "neighborhood_id": "station-north",
      "title": {
        "en": "Sounds of the City"
      },
      "prompt": {
        "en": "Take a photo of something that is making a distinctive sound—a train on the tracks, a band's soundcheck, traffic—and try to convey that sound visually."
      },
      "points": 10,
      "duration_minutes": 5
    },
    {
      "id": "station-north-task-11",
      "neighborhood_id": "station-north",
      "title": {
        "en": "Happy Hour Haven"
      },
      "prompt": {
        "en": "Capture the perfect happy hour scene: a colorful cocktail, some tasty-looking small plates, and a vibrant atmosphere."
      },
      "points": 10,
      "duration_minutes": 5
    },
    {
      "id": "station-north-task-12",
      "neighborhood_id": "station-north",
      "title": {
        "en": "Public Canvas"
      },
      "prompt": {
        "en": "Find a wall that looks like a canvas waiting for an artist. Photograph its blank space and interesting texture."
      },
      "points": 10,
      "duration_minutes": 5
    },
    {
      "id": "station-north-task-13",
      "neighborhood_id": "station-north",
      "title": {
        "en": "Secret Hideout"
      },
      "prompt": {
        "en": "Take a photo of a bar or cafe entrance that looks unassuming or hidden, like a secret spot for those in the know."
      },
      "points": 10,
      "duration_minutes": 5
    },
    {
      "id": "station-north-task-14",
      "neighborhood_id": "station-north",
      "title": {
        "en": "Old Building, New Life"
      },
      "prompt": {
        "en": "Photograph an old, historic building that is clearly being used for a modern, creative purpose (gallery, venue, studio)."
      },
      "points": 10,
      "duration_minutes": 5
    },
    {
      "id": "station-north-task-15",
      "neighborhood_id": "station-north",
      "title": {
        "en": "Streetlight Spotlight"
      },
      "prompt": {
        "en": "Use a streetlight as a spotlight. Take a photo of an object or person dramatically lit by a single streetlamp."
      },
      "points": 10,
      "duration_minutes": 5
    },
    {
      "id": "fells-point-task-1",
      "neighborhood_id": "fells-point",
      "title": {
        "en": "Cobblestone Perspective"
      },
      "prompt": {
        "en": "Get low to the ground and take a photo that emphasizes the texture and pattern of the cobblestone streets."
      },
      "points": 10,
      "duration_minutes": 5
    },
    {
      "id": "fells-point-task-2",
      "neighborhood_id": "fells-point",
      "title": {
        "en": "Maritime Selfie"
      },
      "prompt": {
        "en": "Take a selfie with the historic harbor and its boats in the background. Look like a seasoned sailor!"
      },
      "points": 10,
      "duration_minutes": 5
    },
    {
      "id": "fells-point-task-3",
      "neighborhood_id": "fells-point",
      "title": {
        "en": "Historic Pub Scene"
      },
      "prompt": {
        "en": "Capture the cozy, spirited atmosphere inside one of the neighborhood's old pubs. Focus on the warm lighting and historic details."
      },
      "points": 10,
      "duration_minutes": 5
    },
    {
      "id": "fells-point-task-4",
      "neighborhood_id": "fells-point",
      "title": {
        "en": "Step Back in Time"
      },
      "prompt": {
        "en": "Find a building or street scene that looks like it could be from the 19th century. Take a photo and try editing it in black and white."
      },
      "points": 10,
      "duration_minutes": 5
    },
    {
      "id": "fells-point-task-5",
      "neighborhood_id": "fells-point",
      "title": {
        "en": "Brick and Bloom"
      },
      "prompt": {
        "en": "Find a colorful flower box or climbing ivy set against a historic brick wall and capture the beautiful contrast."
      },
      "points": 10,
      "duration_minutes": 5
    },
    {
      "id": "fells-point-task-6",
      "neighborhood_id": "fells-point",
      "title": {
        "en": "Waterfront Stories"
      },
      "prompt": {
        "en": "Take a photo of an object near the water that seems to have a story—an old rope, a weathered piling, a rusty anchor."
      },
      "points": 10,
      "duration_minutes": 5
    },
    {
      "id": "fells-point-task-7",
      "neighborhood_id": "fells-point",
      "title": {
        "en": "High-Low Pairing"
      },
      "prompt": {
        "en": "Create your own 'high-low' photo. Pair something fancy with something casual, like a nice watch against a rustic pub table."
      },
      "points": 10,
      "duration_minutes": 5
    },
    {
      "id": "fells-point-task-8",
      "neighborhood_id": "fells-point",
      "title": {
        "en": "A Pint with a View"
      },
      "prompt": {
        "en": "If you're having a drink, take a photo of your glass with a view of the cobblestone street or the water in the background."
      },
      "points": 10,
      "duration_minutes": 5
    },
    {
      "id": "fells-point-task-9",
      "neighborhood_id": "fells-point",
      "title": {
        "en": "Historic Marker"
      },
      "prompt": {
        "en": "Find a historical plaque on a building and take a photo of it. What piece of history did you learn?"
      },
      "points": 10,
      "duration_minutes": 5
    },
    {
      "id": "fells-point-task-10",
      "neighborhood_id": "fells-point",
      "title": {
        "en": "Golden Hour Glow"
      },
      "prompt": {
        "en": "During the golden hour (just before sunset), capture the warm light hitting the old brick buildings and cobblestones."
      },
      "points": 10,
      "duration_minutes": 5
    },
    {
      "id": "fells-point-task-11",
      "neighborhood_id": "fells-point",
      "title": {
        "en": "Window to the Past"
      },
      "prompt": {
        "en": "Photograph an old, wavy glass window on a historic building. Try to capture the distorted reflection in it."
      },
      "points": 10,
      "duration_minutes": 5
    },
    {
      "id": "fells-point-task-12",
      "neighborhood_id": "fells-point",
      "title": {
        "en": "Neighborhood Spirit"
      },
      "prompt": {
        "en": "Take a photo of something that represents the 'spirited' vibe of Fell's Point—a lively crowd, a cheerful bartender, or a colorful flag."
      },
      "points": 10,
      "duration_minutes": 5
    },
    {
      "id": "fells-point-task-13",
      "neighborhood_id": "fells-point",
      "title": {
        "en": "Shadows on Cobblestone"
      },
      "prompt": {
        "en": "Capture the long shadows cast by buildings or people across the cobblestone streets late in the afternoon."
      },
      "points": 10,
      "duration_minutes": 5
    },
    {
      "id": "fells-point-task-14",
      "neighborhood_id": "fells-point",
      "title": {
        "en": "Authentic Irish Welcome"
      },
      "prompt": {
        "en": "Find a pub with a sign or entrance that looks genuinely historic and welcoming. Snap a picture of the entrance."
      },
      "points": 10,
      "duration_minutes": 5
    },
    {
      "id": "fells-point-task-15",
      "neighborhood_id": "fells-point",
      "title": {
        "en": "Tugboat Tough"
      },
      "prompt": {
        "en": "Take a photo of one of the tugboats or workboats in the harbor. Try to make it look powerful and hardworking."
      },
      "points": 10,
      "duration_minutes": 5
    },
    {
      "id": "charles-village-waverly-task-1",
      "neighborhood_id": "charles-village-waverly",
      "title": {
        "en": "Academic Atmosphere"
      },
      "prompt": {
        "en": "Take a photo that captures the intellectual, academic energy of the neighborhood. Look for university buildings, students with books, or quiet study spots."
      },
      "points": 10,
      "duration_minutes": 5
    },
    {
      "id": "charles-village-waverly-task-2",
      "neighborhood_id": "charles-village-waverly",
      "title": {
        "en": "Art Lover's Selfie"
      },
      "prompt": {
        "en": "Inside or outside the art museum, take a selfie that shows your appreciation for culture. Pose thoughtfully with a sculpture or interesting architecture."
      },
      "points": 10,
      "duration_minutes": 5
    },
    {
      "id": "charles-village-waverly-task-3",
      "neighborhood_id": "charles-village-waverly",
      "title": {
        "en": "Hidden in Plain Sight"
      },
      "prompt": {
        "en": "Find a restaurant or shop with a very unassuming or plain exterior. Take a photo that makes it look mysterious and intriguing."
      },
      "points": 10,
      "duration_minutes": 5
    },
    {
      "id": "charles-village-waverly-task-4",
      "neighborhood_id": "charles-village-waverly",
      "title": {
        "en": "Baltimore Pride"
      },
      "prompt": {
        "en": "Find a symbol of local Baltimore pride—a flag, a logo on a beer can, a piece of local merch—and make it the hero of your photo."
      },
      "points": 10,
      "duration_minutes": 5
    },
    {
      "id": "charles-village-waverly-task-5",
      "neighborhood_id": "charles-village-waverly",
      "title": {
        "en": "Unpretentiously Cool"
      },
      "prompt": {
        "en": "Capture a scene that feels cool without trying too hard. It could be the way someone has decorated their porch or a laid-back cafe scene."
      },
      "points": 10,
      "duration_minutes": 5
    },
    {
      "id": "charles-village-waverly-task-6",
      "neighborhood_id": "charles-village-waverly",
      "title": {
        "en": "Taste of the Chesapeake"
      },
      "prompt": {
        "en": "Photograph a dish featuring seafood or local produce. Make it look as fresh and delicious as possible."
      },
      "points": 10,
      "duration_minutes": 5
    },
    {
      "id": "charles-village-waverly-task-7",
      "neighborhood_id": "charles-village-waverly",
      "title": {
        "en": "Art Imitates Life"
      },
      "prompt": {
        "en": "Find a scene in the neighborhood (a park, a building, a person) that reminds you of a famous painting and try to replicate the composition."
      },
      "points": 10,
      "duration_minutes": 5
    },
    {
      "id": "charles-village-waverly-task-8",
      "neighborhood_id": "charles-village-waverly",
      "title": {
        "en": "Community Gathering Spot"
      },
      "prompt": {
        "en": "Take a picture of a place where locals are gathering and enjoying their community—a brewery's outdoor space, a park, or a farmer's market."
      },
      "points": 10,
      "duration_minutes": 5
    },
    {
      "id": "charles-village-waverly-task-9",
      "neighborhood_id": "charles-village-waverly",
      "title": {
        "en": "Transportive Experience"
      },
      "prompt": {
        "en": "Find a spot that feels like it could be in a completely different city or country. Capture the details that make it feel transportive."
      },
      "points": 10,
      "duration_minutes": 5
    },
    {
      "id": "charles-village-waverly-task-10",
      "neighborhood_id": "charles-village-waverly",
      "title": {
        "en": "Architectural Contrast"
      },
      "prompt": {
        "en": "Photograph a classic, historic rowhouse next to a more modern university or museum building. Highlight the contrast in styles."
      },
      "points": 10,
      "duration_minutes": 5
    },
    {
      "id": "charles-village-waverly-task-11",
      "neighborhood_id": "charles-village-waverly",
      "title": {
        "en": "Relaxed Energy"
      },
      "prompt": {
        "en": "Take a photo that conveys a sense of calm and relaxation. Look for people reading in a park or enjoying a quiet coffee."
      },
      "points": 10,
      "duration_minutes": 5
    },
    {
      "id": "charles-village-waverly-task-12",
      "neighborhood_id": "charles-village-waverly",
      "title": {
        "en": "Cultural Landmark"
      },
      "prompt": {
        "en": "Take a powerful, dramatic shot of a major cultural institution like the BMA from an interesting angle."
      },
      "points": 10,
      "duration_minutes": 5
    },
    {
      "id": "charles-village-waverly-task-13",
      "neighborhood_id": "charles-village-waverly",
      "title": {
        "en": "Local Brew"
      },
      "prompt": {
        "en": "Get a picture of a locally brewed beer. Focus on the logo, the color of the beer, and the friendly brewery atmosphere."
      },
      "points": 10,
      "duration_minutes": 5
    },
    {
      "id": "charles-village-waverly-task-14",
      "neighborhood_id": "charles-village-waverly",
      "title": {
        "en": "The Perfect Noodle Pull"
      },
      "prompt": {
        "en": "If you're eating ramen or noodles, attempt the perfect 'noodle pull' shot, lifting the noodles enticingly from the bowl."
      },
      "points": 10,
      "duration_minutes": 5
    },
    {
      "id": "charles-village-waverly-task-15",
      "neighborhood_id": "charles-village-waverly",
      "title": {
        "en": "Green Space"
      },
      "prompt": {
        "en": "Find a patch of green amidst the academic buildings and capture a moment of nature in the city."
      },
      "points": 10,
      "duration_minutes": 5
    },
    {
      "id": "mount-vernon-downtown-task-1",
      "neighborhood_id": "mount-vernon-downtown",
      "title": {
        "en": "Gilded Age Grandeur"
      },
      "prompt": {
        "en": "Find the most elegant, grand 19th-century building and take a photo that captures its impressive scale and ornate details."
      },
      "points": 10,
      "duration_minutes": 5
    },
    {
      "id": "mount-vernon-downtown-task-2",
      "neighborhood_id": "mount-vernon-downtown",
      "title": {
        "en": "Hidden Treasure Selfie"
      },
      "prompt": {
        "en": "Take a selfie in front of an unassuming storefront that you know hides a culinary treasure inside. Your expression should say 'I know a secret.'"
      },
      "points": 10,
      "duration_minutes": 5
    },
    {
      "id": "mount-vernon-downtown-task-3",
      "neighborhood_id": "mount-vernon-downtown",
      "title": {
        "en": "Electric Atmosphere"
      },
      "prompt": {
        "en": "Inside a stylish bar, take a photo that captures an 'electric' atmosphere. Focus on moody lighting, cool decor, and the energy of the crowd."
      },
      "points": 10,
      "duration_minutes": 5
    },
    {
      "id": "mount-vernon-downtown-task-4",
      "neighborhood_id": "mount-vernon-downtown",
      "title": {
        "en": "Historic Market Hustle"
      },
      "prompt": {
        "en": "Capture the energy and hustle of a historic public market. Use a slow shutter speed to create motion blur of the shoppers."
      },
      "points": 10,
      "duration_minutes": 5
    },
    {
      "id": "mount-vernon-downtown-task-5",
      "neighborhood_id": "mount-vernon-downtown",
      "title": {
        "en": "Old Meets New"
      },
      "prompt": {
        "en": "Frame a shot that shows the contrast between the historic, grand architecture of Mount Vernon and the modern skyscrapers of the downtown core."
      },
      "points": 10,
      "duration_minutes": 5
    },
    {
      "id": "mount-vernon-downtown-task-6",
      "neighborhood_id": "mount-vernon-downtown",
      "title": {
        "en": "The Essential Bite"
      },
      "prompt": {
        "en": "Take a mouth-watering close-up of an essential Baltimore food, like a crab cake. Make it look like the best thing you've ever eaten."
      },
      "points": 10,
      "duration_minutes": 5
    },
    {
      "id": "mount-vernon-downtown-task-7",
      "neighborhood_id": "mount-vernon-downtown",
      "title": {
        "en": "Urban Discovery"
      },
      "prompt": {
        "en": "Photograph a discreet entrance or alleyway that looks like it leads to a fantastic secret. What makes it so intriguing?"
      },
      "points": 10,
      "duration_minutes": 5
    },
    {
      "id": "mount-vernon-downtown-task-8",
      "neighborhood_id": "mount-vernon-downtown",
      "title": {
        "en": "Stylish & Moody"
      },
      "prompt": {
        "en": "Find a location with stylish, moody decor and take a photo that would fit in an interior design magazine."
      },
      "points": 10,
      "duration_minutes": 5
    },
    {
      "id": "mount-vernon-downtown-task-9",
      "neighborhood_id": "mount-vernon-downtown",
      "title": {
        "en": "A Special Occasion"
      },
      "prompt": {
        "en": "Take a photo of a beautifully presented plate of food or a fancy cocktail that looks perfect for a special occasion."
      },
      "points": 10,
      "duration_minutes": 5
    },
    {
      "id": "mount-vernon-downtown-task-10",
      "neighborhood_id": "mount-vernon-downtown",
      "title": {
        "en": "Sensory Slice of Life"
      },
      "prompt": {
        "en": "At a market, take a photo that appeals to the senses—brightly colored produce, fresh seafood on ice, or the steam from a food stall."
      },
      "points": 10,
      "duration_minutes": 5
    },
    {
      "id": "mount-vernon-downtown-task-11",
      "neighborhood_id": "mount-vernon-downtown",
      "title": {
        "en": "Looking Up"
      },
      "prompt": {
        "en": "Stand at the base of a tall, historic building and take a photo looking straight up to capture its height and architectural details."
      },
      "points": 10,
      "duration_minutes": 5
    },
    {
      "id": "mount-vernon-downtown-task-12",
      "neighborhood_id": "mount-vernon-downtown",
      "title": {
        "en": "Hotel Lobby Elegance"
      },
      "prompt": {
        "en": "Capture the restored historic elegance of a grand hotel lobby. Focus on details like chandeliers, molding, or plush furniture."
      },
      "points": 10,
      "duration_minutes": 5
    },
    {
      "id": "mount-vernon-downtown-task-13",
      "neighborhood_id": "mount-vernon-downtown",
      "title": {
        "en": "The Foodie's Quest"
      },
      "prompt": {
        "en": "Take a photo of a map or your phone's GPS as you search for a hard-to-find restaurant, showing your dedication as a foodie."
      },
      "points": 10,
      "duration_minutes": 5
    },
    {
      "id": "mount-vernon-downtown-task-14",
      "neighborhood_id": "mount-vernon-downtown",
      "title": {
        "en": "Monumental View"
      },
      "prompt": {
        "en": "Frame a shot of a street that has a monument or major landmark perfectly centered at the end of it."
      },
      "points": 10,
      "duration_minutes": 5
    },
    {
      "id": "mount-vernon-downtown-task-15",
      "neighborhood_id": "mount-vernon-downtown",
      "title": {
        "en": "Legendary Institution"
      },
      "prompt": {
        "en": "Photograph a place that has a legendary, institutional feel. It could be a famous food stall, an old hotel, or a cultural center."
      },
      "points": 10,
      "duration_minutes": 5
    }
  ]
}